{
  "updated": 1766511691,
  "items": [
    {
      "id": "f08688b3b8bd",
      "title": "重磅！萬億金融帝國崩塌，中植集團原主席高興山非法吸金罪成，重判14年",
      "url": "https://www.singtaousa.com/2025/12/23/news/china/zhongzhi-former-chairman-sentenced/",
      "source": "singtaousa.com",
      "published": 1766511287
    },
    {
      "id": "d12b71584af7",
      "title": "俄羅斯聖誕前夕對烏克蘭發動大規模空襲 釀3死全國大停電",
      "url": "https://www.singtaousa.com/2025/12/23/news/world/russia-launches-air-attack-kyiv-ukraines-military-says/",
      "source": "singtaousa.com",
      "published": 1766510834
    },
    {
      "id": "428be9640fd7",
      "title": "艾普斯坦新檔案大量涉川普　美司法部斥不實且聳動",
      "url": "https://money.udn.com/money/story/10511/9222683",
      "source": "money.udn.com",
      "published": 1766510491
    },
    {
      "id": "38dda63034b6",
      "title": "合泰興玻璃門窗東灣分公司 開張慶典暨聖誕晚會圓滿舉行",
      "url": "https://www.singtaousa.com/2025/12/23/lifestyle/the-opening-ceremony-and-christmas-party-of-hetaixing-glass-doors-and-windows-dongwan-branch-was-successfully-held/",
      "source": "singtaousa.com",
      "published": 1766510009
    },
    {
      "id": "7ca43f1c4855",
      "title": "合和總會館舉行2025年聖誕聯歡慶會 喜迎聖誕 共賀新年 場面溫馨 歡樂滿堂",
      "url": "https://www.singtaousa.com/2025/12/23/news/usa/the-hopewell-general-hall-held-the-2025-christmas-gala-celebrating-christmas-celebrating-the-new-year-together-the-scene-was-warm-and-the-house-was-full-of-joy/",
      "source": "singtaousa.com",
      "published": 1766509957
    },
    {
      "id": "ea188947a95f",
      "title": "俄軍猛攻敖德薩意圖何在？普京威脅切斷烏克蘭海上通道",
      "url": "https://www.singtaousa.com/2025/12/23/news/world/russia-escalates-attacks-on-key-ukrainian-region-of-odesa/",
      "source": "singtaousa.com",
      "published": 1766509775
    },
    {
      "id": "f69cb576e051",
      "title": "南卡牧師被控網絡跟蹤亡妻，自殺悲劇揭開驚人細節",
      "url": "https://www.singtaousa.com/2025/12/23/news/usa/south-carolina-pastor-charged-with-allegedly-cyberstalking-wife-before-she-died-by-suicide/",
      "source": "singtaousa.com",
      "published": 1766509659
    },
    {
      "id": "300b7910a08d",
      "title": "美中科技戰再升級！美國宣布2027年起對中國晶片加徵關稅，特朗普：強化國家安全",
      "url": "https://www.singtaousa.com/2025/12/23/news/china/us-china-tariffs-semiconductors-2027/",
      "source": "singtaousa.com",
      "published": 1766509488
    },
    {
      "id": "9dd1f5617566",
      "title": "特朗普政府突喊停東岸風電，國安風險說法背後有何玄機？",
      "url": "https://www.singtaousa.com/2025/12/23/news/usa/trump-administration-suspends-5-wind-projects-off-the-east-coast-cites-national-security-concerns/",
      "source": "singtaousa.com",
      "published": 1766508422
    },
    {
      "id": "da2882bf15d6",
      "title": "美國第3季經濟成長率4.3%　高於市場預期",
      "url": "https://money.udn.com/money/story/10511/9222665",
      "source": "money.udn.com",
      "published": 1766508298
    },
    {
      "id": "43294fae2df9",
      "title": "特朗普「大而美法案」如何影響您的退稅？四大減稅亮點全解析",
      "url": "https://www.singtaousa.com/2025/12/23/lifestyle/finance/heres-how-trumps-big-beautiful-bill-could-impact-your-tax-refunds-in-april/",
      "source": "singtaousa.com",
      "published": 1766508063
    },
    {
      "id": "6e1bdc14c635",
      "title": "夯品現象 1／2026年六大暢銷品是這些？透視二社會現象，現代年輕人竟這樣想",
      "url": "https://money.udn.com/money/story/122979/9179893",
      "source": "money.udn.com",
      "published": 1766505819
    },
    {
      "id": "79d5abc2213e",
      "title": "快讯：美国将于2027年6月起对中国芯片加征关税",
      "url": "https://www.rfi.fr/cn/%E4%B8%AD%E5%9B%BD/20251223-%E5%BF%AB%E8%AE%AF-%E7%BE%8E%E5%9B%BD%E5%B0%86%E4%BA%8E2027%E5%B9%B46%E6%9C%88%E8%B5%B7%E5%AF%B9%E4%B8%AD%E5%9B%BD%E8%8A%AF%E7%89%87%E5%8A%A0%E5%BE%81%E5%85%B3%E7%A8%8E",
      "source": "rfi.fr",
      "published": 1766505452
    },
    {
      "id": "e2e5487d0970",
      "title": "纽约州前华裔官员间谍案程序作废",
      "url": "https://www.dw.com/zh/纽约州前华裔官员间谍案程序作废/a-75289233?maca=chi-rss-chi-all-1127-rdf",
      "source": "dw.com",
      "published": 1766505000
    },
    {
      "id": "c97f12e85d29",
      "title": "马克龙回击美国觊觎：格陵兰属于其人民，丹麦是其守护者",
      "url": "https://www.rfi.fr/cn/%E6%AC%A7%E6%B4%B2/20251223-%E9%A9%AC%E5%85%8B%E9%BE%99%E5%9B%9E%E5%87%BB%E7%BE%8E%E5%9B%BD%E8%A7%8A%E8%A7%8E-%E6%A0%BC%E9%99%B5%E5%85%B0%E5%B1%9E%E4%BA%8E%E5%85%B6%E4%BA%BA%E6%B0%91%EF%BC%8C%E4%B8%B9%E9%BA%A6%E6%98%AF%E5%85%B6%E5%AE%88%E6%8A%A4%E8%80%85",
      "source": "rfi.fr",
      "published": 1766504561
    },
    {
      "id": "d5d17119217d",
      "title": "不顾欧洲反对，特朗普坚称：面对中俄威胁 美国“需要”格陵兰",
      "url": "https://www.rfi.fr/cn/%E7%BE%8E%E6%B4%B2/20251223-%E4%B8%8D%E9%A1%BE%E6%AC%A7%E6%B4%B2%E5%8F%8D%E5%AF%B9%EF%BC%8C%E7%89%B9%E6%9C%97%E6%99%AE%E5%9D%9A%E7%A7%B0-%E9%9D%A2%E5%AF%B9%E4%B8%AD%E4%BF%84%E5%A8%81%E8%83%81-%E7%BE%8E%E5%9B%BD-%E9%9C%80%E8%A6%81-%E6%A0%BC%E9%99%B5%E5%85%B0",
      "source": "rfi.fr",
      "published": 1766504426
    },
    {
      "id": "2b1a0c871183",
      "title": "美國貿易代表署：2027年中起將對中國晶片加徵關稅",
      "url": "https://money.udn.com/money/story/5599/9222567",
      "source": "money.udn.com",
      "published": 1766503835
    },
    {
      "id": "bd0e4569cb75",
      "title": "大雨暴洪襲北加州1死  南加州也將迎潮濕耶誕節",
      "url": "https://money.udn.com/money/story/10511/9222516",
      "source": "money.udn.com",
      "published": 1766503292
    },
    {
      "id": "0f4af5dcdd9f",
      "title": "特朗普再施压委内瑞拉 俄罗斯力挺马杜罗",
      "url": "https://www.rfi.fr/cn/%E4%B8%93%E6%A0%8F%E6%A3%80%E7%B4%A2/%E8%A6%81%E9%97%BB%E8%A7%A3%E8%AF%B4/20251223-%E7%89%B9%E6%9C%97%E6%99%AE%E5%86%8D%E6%96%BD%E5%8E%8B%E5%A7%94%E5%86%85%E7%91%9E%E6%8B%89-%E4%BF%84%E7%BD%97%E6%96%AF%E5%8A%9B%E6%8C%BA%E9%A9%AC%E6%9D%9C%E7%BD%97",
      "source": "rfi.fr",
      "published": 1766503120
    },
    {
      "id": "635be57bf803",
      "title": "英国警方逮捕“气候女孩”通贝里",
      "url": "https://www.dw.com/zh/英国警方逮捕-气候女孩-通贝里/a-75289078?maca=chi-rss-chi-all-1127-rdf",
      "source": "dw.com",
      "published": 1766502900
    },
    {
      "id": "5dc0e777fb66",
      "title": "美股早盤／美擬2027年6月起對陸輸美晶片加徵關稅 晶片股應聲翻黑",
      "url": "https://money.udn.com/money/story/123398/9222458",
      "source": "money.udn.com",
      "published": 1766502344
    },
    {
      "id": "691d2758115e",
      "title": "美貿易代表署：2027年中將對來自中國晶片 徵新關稅",
      "url": "https://money.udn.com/money/story/5599/9222431",
      "source": "money.udn.com",
      "published": 1766501552
    },
    {
      "id": "094ad87cc481",
      "title": "德语媒体：危险的依赖与可能的错误",
      "url": "https://www.dw.com/zh/德语媒体：危险的依赖与可能的错误/a-75288471?maca=chi-rss-chi-all-1127-rdf",
      "source": "dw.com",
      "published": 1766501520
    },
    {
      "id": "8b6e659c35fe",
      "title": "NHK：福井縣核電廠含氚水外洩　輻射監測未發現異常",
      "url": "https://money.udn.com/money/story/5599/9222417",
      "source": "money.udn.com",
      "published": 1766501188
    },
    {
      "id": "f4b2b70302d9",
      "title": "遊戲巨擘贊佩拉魂斷山路 法拉利撞毀背後原因未明",
      "url": "https://www.singtaousa.com/2025/12/23/news/usa/vince-zampella-video-game-developer-behind-call-of-duty-franchise-killed-in-ferrari-crash/",
      "source": "singtaousa.com",
      "published": 1766500704
    },
    {
      "id": "d44ebf71bee5",
      "title": "金價到底漲什麼勁？「避險」論太老套  學者揭這個單純因素",
      "url": "https://money.udn.com/money/story/5599/9222398",
      "source": "money.udn.com",
      "published": 1766500650
    },
    {
      "id": "b96846ccc6d0",
      "title": "光伏与IT贸易争端：中国向世贸组织状告印度歧视性措施",
      "url": "https://www.rfi.fr/cn/%E4%B8%AD%E5%9B%BD/20251223-%E5%85%89%E4%BC%8F%E4%B8%8Eit%E8%B4%B8%E6%98%93%E4%BA%89%E7%AB%AF-%E4%B8%AD%E5%9B%BD%E5%90%91%E4%B8%96%E8%B4%B8%E7%BB%84%E7%BB%87%E7%8A%B6%E5%91%8A%E5%8D%B0%E5%BA%A6%E6%AD%A7%E8%A7%86%E6%80%A7%E6%8E%AA%E6%96%BD",
      "source": "rfi.fr",
      "published": 1766500061
    },
    {
      "id": "2f49b43102a2",
      "title": "美Q3 GDP成長4.3% 兩年來最強表現",
      "url": "https://money.udn.com/money/story/5599/9222342",
      "source": "money.udn.com",
      "published": 1766498614
    },
    {
      "id": "86ed9cdba192",
      "title": "路透独家：五角大楼报告称中国部署了百余枚洲际弹道导弹",
      "url": "https://www.dw.com/zh/路透独家：五角大楼报告称中国部署了百余枚洲际弹道导弹/a-75285479?maca=chi-rss-chi-all-1127-rdf",
      "source": "dw.com",
      "published": 1766498580
    },
    {
      "id": "3a91e9893487",
      "title": "荣鼎智库：中国经济实际增长仅为官方数据一半",
      "url": "https://www.dw.com/zh/荣鼎智库：中国经济实际增长仅为官方数据一半/a-75286840?maca=chi-rss-chi-all-1127-rdf",
      "source": "dw.com",
      "published": 1766498220
    },
    {
      "id": "67f7e80e8708",
      "title": "德國遣返敘利亞人　2011年以來首見",
      "url": "https://money.udn.com/money/story/5599/9222301",
      "source": "money.udn.com",
      "published": 1766497529
    },
    {
      "id": "898f6431350a",
      "title": "DRAM 技術外流中國長鑫存儲 韓起訴前三星員工等10人",
      "url": "https://money.udn.com/money/story/5599/9222290",
      "source": "money.udn.com",
      "published": 1766496974
    },
    {
      "id": "43799136cdad",
      "title": "烏克蘭：俄635架無人機38枚飛彈來襲　釀3死及大停電",
      "url": "https://money.udn.com/money/story/5599/9222274",
      "source": "money.udn.com",
      "published": 1766495548
    },
    {
      "id": "1d4d2c1cc5e5",
      "title": "英國第3季度經濟增速放緩 但儲蓄率下降表明消費者謹慎情緒緩解",
      "url": "https://money.udn.com/money/story/5599/9220416",
      "source": "money.udn.com",
      "published": 1766495255
    },
    {
      "id": "12960e5f6e2d",
      "title": "柬埔寨欲在吉隆坡舉行停火協商　泰方拒絕更改地點",
      "url": "https://money.udn.com/money/story/5599/9222271",
      "source": "money.udn.com",
      "published": 1766495205
    },
    {
      "id": "6941d18e43b1",
      "title": "川普宣布打造「川普級」軍艦 推動黃金艦隊計畫",
      "url": "https://money.udn.com/money/story/5599/9220461",
      "source": "money.udn.com",
      "published": 1766494380
    },
    {
      "id": "efef2c5425fc",
      "title": "白宫：自今年1月以来关税收入达2350亿美元",
      "url": "https://www.dw.com/zh/白宫：自今年1月以来关税收入达2350亿美元/a-75264979?maca=chi-rss-chi-all-1127-rdf",
      "source": "dw.com",
      "published": 1766494260
    },
    {
      "id": "e0e53082d2b3",
      "title": "贸易战升级：中国对欧盟乳制品征收惩罚性关税",
      "url": "https://www.dw.com/zh/贸易战升级：中国对欧盟乳制品征收惩罚性关税/a-75270646?maca=chi-rss-chi-all-1127-rdf",
      "source": "dw.com",
      "published": 1766494260
    },
    {
      "id": "c1c4dff897ab",
      "title": "外國製無人機存國安風險 大疆遭美限制進口",
      "url": "https://www.dw.com/zh/外國製無人機存國安風險-大疆遭美限制進口/a-75277851?maca=chi-rss-chi-all-1127-rdf",
      "source": "dw.com",
      "published": 1766494260
    },
    {
      "id": "5ad03eb421ef",
      "title": "孟加拉民眾私刑殺害印度教男子　新德里數百人抗議",
      "url": "https://money.udn.com/money/story/5599/9222250",
      "source": "money.udn.com",
      "published": 1766493949
    },
    {
      "id": "62c2255bab0e",
      "title": "黑石集團收購澳洲大堡礁核心區度假島",
      "url": "https://money.udn.com/money/story/5599/9221498",
      "source": "money.udn.com",
      "published": 1766492762
    },
    {
      "id": "1b688eafc6c1",
      "title": "美印關係產生裂痕 川普與莫迪的友誼為何正在走向終結？",
      "url": "https://money.udn.com/money/story/120769/9221466",
      "source": "money.udn.com",
      "published": 1766492755
    },
    {
      "id": "b68489487afe",
      "title": "东部中部战区司令员获擢拔上将 预示习近平对台、对内两手考量？",
      "url": "https://www.rfi.fr/cn/%E4%B8%AD%E5%9B%BD/20251223-%E4%B8%9C%E9%83%A8%E4%B8%AD%E9%83%A8%E6%88%98%E5%8C%BA%E5%8F%B8%E4%BB%A4%E5%91%98%E8%8E%B7%E6%93%A2%E6%8B%94%E4%B8%8A%E5%B0%86-%E9%A2%84%E7%A4%BA%E4%B9%A0%E8%BF%91%E5%B9%B3%E5%AF%B9%E5%8F%B0-%E5%AF%B9%E5%86%85%E4%B8%A4%E6%89%8B%E8%80%83%E9%87%8F",
      "source": "rfi.fr",
      "published": 1766492348
    },
    {
      "id": "2f5d10a20651",
      "title": "对赌特朗普：华尔街兴起“关税退款”交易",
      "url": "https://www.dw.com/zh/对赌特朗普：华尔街兴起-关税退款-交易/a-75285226?maca=chi-rss-chi-all-1127-rdf",
      "source": "dw.com",
      "published": 1766491980
    },
    {
      "id": "81cc7ec3513e",
      "title": "美國司法部再公布艾普斯坦檔案　逾8000份新文件上網",
      "url": "https://money.udn.com/money/story/5599/9222188",
      "source": "money.udn.com",
      "published": 1766491950
    },
    {
      "id": "080153881e3a",
      "title": "泽连斯基：“重要的是美方能促成俄罗斯做出回应”",
      "url": "https://www.dw.com/zh/泽连斯基：-重要的是美方能促成俄罗斯做出回应/a-75283816?maca=chi-rss-chi-all-1127-rdf",
      "source": "dw.com",
      "published": 1766490540
    },
    {
      "id": "6aba9a6cfd9b",
      "title": "科威特联手中国，41亿美元共建穆巴拉克港",
      "url": "https://www.rfi.fr/cn/%E4%B8%AD%E5%9B%BD/20251223-%E7%A7%91%E5%A8%81%E7%89%B9%E8%81%94%E6%89%8B%E4%B8%AD%E5%9B%BD%EF%BC%8C41%E4%BA%BF%E7%BE%8E%E5%85%83%E5%85%B1%E5%BB%BA%E7%A9%86%E5%B7%B4%E6%8B%89%E5%85%8B%E6%B8%AF",
      "source": "rfi.fr",
      "published": 1766490468
    },
    {
      "id": "d65c51ad4127",
      "title": "美智库估中国今年实质经济增长率介于2.5%至3% 约官宣的一半",
      "url": "https://www.rfi.fr/cn/%E4%B8%AD%E5%9B%BD/20251223-%E7%BE%8E%E6%99%BA%E5%BA%93%E4%BC%B0%E4%B8%AD%E5%9B%BD%E4%BB%8A%E5%B9%B4%E5%AE%9E%E8%B4%A8%E7%BB%8F%E6%B5%8E%E5%A2%9E%E9%95%BF%E7%8E%87%E4%BB%8B%E4%BA%8E2-5-%E8%87%B33-%E7%BA%A6%E5%AE%98%E5%AE%A3%E7%9B%AE%E6%A0%87%E7%9A%84%E4%B8%80%E5%8D%8A",
      "source": "rfi.fr",
      "published": 1766489703
    },
    {
      "id": "6765ef9226e5",
      "title": "继美参议院后 众议院也提交支持日本决议案",
      "url": "https://www.rfi.fr/cn/%E4%B8%AD%E5%9B%BD/20251223-%E7%BB%A7%E7%BE%8E%E5%8F%82%E8%AE%AE%E9%99%A2%E5%90%8E-%E4%BC%97%E8%AE%AE%E9%99%A2%E4%B9%9F%E6%8F%90%E4%BA%A4%E6%94%AF%E6%8C%81%E6%97%A5%E6%9C%AC%E5%86%B3%E8%AE%AE%E6%A1%88",
      "source": "rfi.fr",
      "published": 1766487156
    },
    {
      "id": "70544c865b23",
      "title": "德国2025：总理默茨的声望持续下跌",
      "url": "https://www.rfi.fr/cn/%E4%B8%93%E6%A0%8F%E6%A3%80%E7%B4%A2/%E6%9F%8F%E6%9E%97%E9%A3%9E%E9%B8%BF/20251223-%E5%BE%B7%E5%9B%BD2025-%E6%80%BB%E7%90%86%E9%BB%98%E8%8C%A8%E7%9A%84%E5%A3%B0%E6%9C%9B%E6%8C%81%E7%BB%AD%E4%B8%8B%E8%B7%8C",
      "source": "rfi.fr",
      "published": 1766485060
    },
    {
      "id": "cabc46fd54f1",
      "title": "浙江5個月女嬰「心臟病」手術不治，引發誤診爭議和社會大討論",
      "url": "https://www.bbc.com/zhongwen/articles/c2eplyw4ykjo/trad?at_medium=RSS&at_campaign=rss",
      "source": "bbc.com",
      "published": 1766483199
    },
    {
      "id": "8d8dc54fd6f3",
      "title": "零食如何改變了我們的飲食方式？",
      "url": "https://www.bbc.com/zhongwen/articles/cvg17z3z2elo/trad?at_medium=RSS&at_campaign=rss",
      "source": "bbc.com",
      "published": 1766480628
    },
    {
      "id": "f9874437e270",
      "title": "美国禁止大疆等外国无人机新机型进口及在美销售",
      "url": "https://www.rfi.fr/cn/%E5%9B%BD%E9%99%85/20251223-%E7%BE%8E%E5%9B%BD%E7%A6%81%E6%AD%A2%E5%A4%A7%E7%96%86%E7%AD%89%E5%A4%96%E5%9B%BD%E6%97%A0%E4%BA%BA%E6%9C%BA%E6%96%B0%E6%9C%BA%E5%9E%8B%E8%BF%9B%E5%8F%A3%E5%8F%8A%E5%9C%A8%E7%BE%8E%E9%94%80%E5%94%AE",
      "source": "rfi.fr",
      "published": 1766480513
    },
    {
      "id": "590dd3785ee0",
      "title": "特朗普宣布建造“Trump”等级能携带极音速和核导弹的全新型战舰：“用来应对所有人不只中国”",
      "url": "https://www.rfi.fr/cn/%E7%BE%8E%E6%B4%B2/20251223-%E7%89%B9%E6%9C%97%E6%99%AE%E5%AE%A3%E5%B8%83%E5%BB%BA%E9%80%A0-trump-%E7%AD%89%E7%BA%A7%E8%83%BD%E6%90%BA%E5%B8%A6%E6%9E%81%E9%9F%B3%E9%80%9F%E5%92%8C%E6%A0%B8%E5%AF%BC%E5%BC%B9%E7%9A%84%E5%85%A8%E6%96%B0%E5%9E%8B%E6%88%98%E8%88%B0-%E7%94%A8%E6%9D%A5%E5%AF%B9%E4%BB%98%E6%89%80%E6%9C%89%E4%BA%BA%E4%B8%8D%E5%8F%AA%E4%B8%AD%E5%9B%BD",
      "source": "rfi.fr",
      "published": 1766479204
    },
    {
      "id": "a68a8956312e",
      "title": "在野黨發動彈劾賴清德 「600萬人網路連署」是真的嗎？",
      "url": "https://www.dw.com/zh/在野黨發動彈劾賴清德-「600萬人網路連署」是真的嗎？/a-75279487?maca=chi-rss-chi-all-1127-rdf",
      "source": "dw.com",
      "published": 1766478300
    },
    {
      "id": "ebcd47a93f8b",
      "title": "「那一刻，戰爭暫停了」：第一次世界大戰聖誕節自發停戰的故事",
      "url": "https://www.bbc.com/zhongwen/articles/cj9ydg17ezdo/trad?at_medium=RSS&at_campaign=rss",
      "source": "bbc.com",
      "published": 1766477089
    },
    {
      "id": "22e71b9d7b25",
      "title": "受政治对立影响 明年1月日中往返航班取消超2000",
      "url": "https://www.rfi.fr/cn/%E6%94%BF%E6%B2%BB/20251223-%E5%8F%97%E6%94%BF%E6%B2%BB%E5%AF%B9%E7%AB%8B%E5%BD%B1%E5%93%8D-%E6%98%8E%E5%B9%B41%E6%9C%88%E6%97%A5%E4%B8%AD%E5%BE%80%E8%BF%94%E8%88%AA%E7%8F%AD%E5%8F%96%E6%B6%88%E8%B6%852000",
      "source": "rfi.fr",
      "published": 1766476669
    },
    {
      "id": "2513d1c2e4e6",
      "title": "终审庭前法官批黎智英案是香港走向极权标志 中方续就批评向英美提交涉",
      "url": "https://www.rfi.fr/cn/%E4%B8%AD%E5%9B%BD/20251223-%E7%BB%88%E5%AE%A1%E5%BA%AD%E5%89%8D%E6%B3%95%E5%AE%98%E6%89%B9%E9%BB%8E%E6%99%BA%E8%8B%B1%E6%A1%88%E6%98%AF%E9%A6%99%E6%B8%AF%E8%B5%B0%E5%90%91%E6%9E%81%E6%9D%83%E6%A0%87%E5%BF%97-%E4%B8%AD%E6%96%B9%E7%BB%AD%E5%B0%B1%E6%89%B9%E8%AF%84%E5%90%91%E8%8B%B1%E7%BE%8E%E6%8F%90%E4%BA%A4%E6%B6%89",
      "source": "rfi.fr",
      "published": 1766474562
    },
    {
      "id": "4adfaf5a89c7",
      "title": "毛絨玩具如何征服童心未泯的成年人",
      "url": "https://www.bbc.com/zhongwen/articles/cvgr072z1e0o/trad?at_medium=RSS&at_campaign=rss",
      "source": "bbc.com",
      "published": 1766470473
    },
    {
      "id": "fe9a97b9484d",
      "title": "特朗普：美國「必須擁有」格陵蘭",
      "url": "https://www.bbc.com/zhongwen/articles/c5yqw99nv42o/trad?at_medium=RSS&at_campaign=rss",
      "source": "bbc.com",
      "published": 1766468891
    },
    {
      "id": "f734f9191052",
      "title": "俄羅斯對烏克蘭敖德薩的襲擊升級，危及海運重要通道",
      "url": "https://www.bbc.com/zhongwen/articles/ckg96x85gzgo/trad?at_medium=RSS&at_campaign=rss",
      "source": "bbc.com",
      "published": 1766465321
    },
    {
      "id": "d529798f0734",
      "title": "年增百枚核弹头：中国发射井数已超美国，2026全球“核军控”滑向“核失控”？",
      "url": "https://www.rfi.fr/cn/%E4%B8%AD%E5%9B%BD/20251223-%E5%B9%B4%E5%A2%9E%E7%99%BE%E6%9E%9A%E6%A0%B8%E5%BC%B9%E5%A4%B4-%E4%B8%AD%E5%9B%BD%E5%8F%91%E5%B0%84%E4%BA%95%E6%95%B0%E5%B7%B2%E8%B6%85%E7%BE%8E%E5%9B%BD%EF%BC%8C2026%E5%85%A8%E7%90%83-%E6%A0%B8%E5%86%9B%E6%8E%A7-%E6%BB%91%E5%90%91-%E6%A0%B8%E5%A4%B1%E6%8E%A7",
      "source": "rfi.fr",
      "published": 1766456057
    },
    {
      "id": "0a8bc7afb53b",
      "title": "傳統中醫何以扎根港澳等地？「疑中醫論」陰影下公眾信心從何而來？",
      "url": "https://www.bbc.com/zhongwen/articles/c4g98533404o/trad?at_medium=RSS&at_campaign=rss",
      "source": "bbc.com",
      "published": 1766449329
    },
    {
      "id": "8b3ffd6e3d7b",
      "title": "德贸易协会：中国关税“是一次重大打击”",
      "url": "https://www.rfi.fr/cn/%E4%B8%AD%E5%9B%BD/20251222-%E5%BE%B7%E8%B4%B8%E6%98%93%E5%8D%8F%E4%BC%9A-%E4%B8%AD%E5%9B%BD%E5%85%B3%E7%A8%8E-%E6%98%AF%E4%B8%80%E6%AC%A1%E9%87%8D%E5%A4%A7%E6%89%93%E5%87%BB",
      "source": "rfi.fr",
      "published": 1766438923
    },
    {
      "id": "7a0ca545a0fa",
      "title": "圣诞节前   京东在巴黎郊区的库存被盗     损失3.700万欧",
      "url": "https://www.rfi.fr/cn/%E6%B3%95%E5%9B%BD/20251222-%E5%9C%A3%E8%AF%9E%E8%8A%82%E5%89%8D-%E4%BA%AC%E4%B8%9C%E5%9C%A8%E5%B7%B4%E9%BB%8E%E9%83%8A%E5%8C%BA%E7%9A%84%E5%BA%93%E5%AD%98%E8%A2%AB%E7%9B%97-%E6%8D%9F%E5%A4%B13-700%E4%B8%87%E6%AC%A7",
      "source": "rfi.fr",
      "published": 1766438699
    },
    {
      "id": "aaeb52327552",
      "title": "英美媒体：中国催生政策“令人费解”",
      "url": "https://www.rfi.fr/cn/%E4%B8%AD%E5%9B%BD/20251222-%E8%8B%B1%E7%BE%8E%E5%AA%92%E4%BD%93-%E4%B8%AD%E5%9B%BD%E5%82%AC%E7%94%9F%E6%94%BF%E7%AD%96-%E4%BB%A4%E4%BA%BA%E8%B4%B9%E8%A7%A3",
      "source": "rfi.fr",
      "published": 1766438519
    },
    {
      "id": "327c6d4c3e16",
      "title": "特朗普政府暂停美国所有海上风电项目",
      "url": "https://www.rfi.fr/cn/%E7%BE%8E%E6%B4%B2/20251222-%E7%89%B9%E6%9C%97%E6%99%AE%E6%94%BF%E5%BA%9C%E6%9A%82%E5%81%9C%E7%BE%8E%E5%9B%BD%E6%89%80%E6%9C%89%E6%B5%B7%E4%B8%8A%E9%A3%8E%E7%94%B5%E9%A1%B9%E7%9B%AE",
      "source": "rfi.fr",
      "published": 1766438262
    },
    {
      "id": "85acd808321d",
      "title": "特朗普要召回多名拜登任命的驻外大使",
      "url": "https://www.rfi.fr/cn/%E7%BE%8E%E6%B4%B2/20251222-%E7%89%B9%E6%9C%97%E6%99%AE%E8%A6%81%E5%8F%AC%E5%9B%9E%E5%A4%9A%E5%90%8D%E6%8B%9C%E7%99%BB%E4%BB%BB%E5%91%BD%E7%9A%84%E9%A9%BB%E5%A4%96%E5%A4%A7%E4%BD%BF",
      "source": "rfi.fr",
      "published": 1766438021
    },
    {
      "id": "195d1737069f",
      "title": "特朗普委任格陵兰岛特使      丹麦召见美国大使",
      "url": "https://www.rfi.fr/cn/%E6%AC%A7%E6%B4%B2/20251222-%E7%89%B9%E6%9C%97%E6%99%AE%E5%A7%94%E4%BB%BB%E6%A0%BC%E9%99%B5%E5%85%B0%E5%B2%9B%E7%89%B9%E4%BD%BF-%E4%B8%B9%E9%BA%A6%E5%8F%AC%E8%A7%81%E7%BE%8E%E5%9B%BD%E5%A4%A7%E4%BD%BF",
      "source": "rfi.fr",
      "published": 1766437848
    },
    {
      "id": "0d5690a04a39",
      "title": "儿童色情玩偶：一英网站被举报",
      "url": "https://www.rfi.fr/cn/%E5%9B%BD%E9%99%85/20251222-%E5%84%BF%E7%AB%A5%E8%89%B2%E6%83%85%E7%8E%A9%E5%81%B6-%E4%B8%80%E8%8B%B1%E7%BD%91%E7%AB%99%E8%A2%AB%E4%B8%BE%E6%8A%A5",
      "source": "rfi.fr",
      "published": 1766437622
    },
    {
      "id": "7dfff2f08dff",
      "title": "法邮政遭网攻   现已恢复正常",
      "url": "https://www.rfi.fr/cn/%E6%B3%95%E5%9B%BD/20251222-%E6%B3%95%E9%82%AE%E6%94%BF%E9%81%AD%E7%BD%91%E6%94%BB-%E7%8E%B0%E5%B7%B2%E6%81%A2%E5%A4%8D%E6%AD%A3%E5%B8%B8",
      "source": "rfi.fr",
      "published": 1766437461
    },
    {
      "id": "f88066be3afa",
      "title": "俄罗斯高级军事将领被暗杀，是否有西方情报机构的参与？",
      "url": "https://www.rfi.fr/cn/%E4%B8%93%E6%A0%8F%E6%A3%80%E7%B4%A2/%E8%A6%81%E9%97%BB%E5%88%86%E6%9E%90/20251222-%E4%BF%84%E7%BD%97%E6%96%AF%E9%AB%98%E7%BA%A7%E5%86%9B%E4%BA%8B%E5%B0%86%E9%A2%86%E8%A2%AB%E6%9A%97%E6%9D%80%EF%BC%8C%E6%98%AF%E5%90%A6%E6%9C%89%E8%A5%BF%E6%96%B9%E6%83%85%E6%8A%A5%E6%9C%BA%E6%9E%84%E7%9A%84%E5%8F%82%E4%B8%8E",
      "source": "rfi.fr",
      "published": 1766433141
    },
    {
      "id": "40289bc699bc",
      "title": "特朗普将发表造船谈话 美军“黄金舰队”敏捷型巡防舰计划受瞩目",
      "url": "https://www.rfi.fr/cn/%E6%94%BF%E6%B2%BB/20251222-%E7%89%B9%E6%9C%97%E6%99%AE%E5%B0%86%E5%8F%91%E8%A1%A8%E9%80%A0%E8%88%B9%E8%B0%88%E8%AF%9D-%E7%BE%8E%E5%86%9B-%E9%BB%84%E9%87%91%E8%88%B0%E9%98%9F-%E6%95%8F%E6%8D%B7%E5%9E%8B%E5%B7%A1%E9%98%B2%E8%88%B0%E8%AE%A1%E5%88%92%E5%8F%97%E7%9E%A9%E7%9B%AE",
      "source": "rfi.fr",
      "published": 1766431798
    },
    {
      "id": "d86abe6d7306",
      "title": "法国里昂附近一家化工厂发生爆炸 至少4人受伤",
      "url": "https://www.rfi.fr/cn/%E7%A4%BE%E4%BC%9A/20251222-%E6%B3%95%E5%9B%BD%E9%87%8C%E6%98%82%E9%99%84%E8%BF%91%E4%B8%80%E5%AE%B6%E5%8C%96%E5%B7%A5%E5%8E%82%E5%8F%91%E7%94%9F%E7%88%86%E7%82%B8-%E8%87%B3%E5%B0%914%E4%BA%BA%E5%8F%97%E4%BC%A4",
      "source": "rfi.fr",
      "published": 1766425471
    },
    {
      "id": "55817fdbe143",
      "title": "《自杀通告》“不利国安”被禁 香港导演周冠威：荒谬至极",
      "url": "https://www.rfi.fr/cn/%E6%B8%AF%E6%BE%B3%E5%8F%B0/20251222-%E8%87%AA%E6%9D%80%E9%80%9A%E5%91%8A-%E4%B8%8D%E5%88%A9%E5%9B%BD%E5%AE%89-%E8%A2%AB%E7%A6%81-%E9%A6%99%E6%B8%AF%E5%AF%BC%E6%BC%94%E5%91%A8%E5%86%A0%E5%A8%81-%E8%8D%92%E8%B0%AC%E8%87%B3%E6%9E%81",
      "source": "rfi.fr",
      "published": 1766422239
    },
    {
      "id": "376cadeef0e2",
      "title": "英伟达H200拟春节前向中供货，腾讯借道日本获美尖端算力",
      "url": "https://www.rfi.fr/cn/%E4%B8%AD%E5%9B%BD/20251222-%E8%8B%B1%E4%BC%9F%E8%BE%BEh200%E6%8B%9F%E6%98%A5%E8%8A%82%E5%89%8D%E5%90%91%E4%B8%AD%E4%BE%9B%E8%B4%A7%EF%BC%8C%E8%85%BE%E8%AE%AF%E5%80%9F%E9%81%93%E6%97%A5%E6%9C%AC%E8%8E%B7%E7%BE%8E%E5%B0%96%E7%AB%AF%E7%AE%97%E5%8A%9B",
      "source": "rfi.fr",
      "published": 1766419901
    },
    {
      "id": "40464b9203e3",
      "title": "币安未能阻止可疑账户继续交易",
      "url": "https://www.ftchinese.com/story/001108518",
      "source": "ftchinese.com",
      "published": 1766419200
    },
    {
      "id": "430d2a8fdd56",
      "title": "港股芯片潮驶入AI赛道 天数智芯加入战局",
      "url": "https://www.ftchinese.com/story/001108517",
      "source": "ftchinese.com",
      "published": 1766419200
    },
    {
      "id": "c7c8e572c374",
      "title": "股价闪崩市值腰斩 曹操出行背后的隐忧",
      "url": "https://www.ftchinese.com/story/001108516",
      "source": "ftchinese.com",
      "published": 1766419200
    },
    {
      "id": "9eb337a113f6",
      "title": "字节跳动计划明年投入1600亿元人民币资本支出",
      "url": "https://www.ftchinese.com/story/001108514",
      "source": "ftchinese.com",
      "published": 1766419200
    },
    {
      "id": "f06ac288b346",
      "title": "“中等强国”进入充满不确定性的新时代",
      "url": "https://www.ftchinese.com/story/001108513",
      "source": "ftchinese.com",
      "published": 1766419200
    },
    {
      "id": "130412704576",
      "title": "Lex专栏：美国媒体行业的另一场并购大戏",
      "url": "https://www.ftchinese.com/story/001108511",
      "source": "ftchinese.com",
      "published": 1766419200
    },
    {
      "id": "a3b457d5ee39",
      "title": "经济、金融的“双周期”：由合而分",
      "url": "https://www.ftchinese.com/story/001108500",
      "source": "ftchinese.com",
      "published": 1766419200
    },
    {
      "id": "3c25e586327b",
      "title": "日本留学“性价比神话”破灭",
      "url": "https://www.ftchinese.com/story/001108456",
      "source": "ftchinese.com",
      "published": 1766419200
    },
    {
      "id": "85f3b6c44dcb",
      "title": "高净值家庭的代际困境(一）：被围猎的二代",
      "url": "https://www.ftchinese.com/story/001108503",
      "source": "ftchinese.com",
      "published": 1766419200
    },
    {
      "id": "0437c1fdc25c",
      "title": "“独身女子逝世，买不买墓碑”的背后，是丧葬制度",
      "url": "https://www.ftchinese.com/story/001108504",
      "source": "ftchinese.com",
      "published": 1766419200
    },
    {
      "id": "8386f20db192",
      "title": "信息披露监管手段的泛化使用和合理边界的选择",
      "url": "https://www.ftchinese.com/story/001108506",
      "source": "ftchinese.com",
      "published": 1766419200
    },
    {
      "id": "4ebb57428109",
      "title": "俄罗斯又一高级军官遭汽车炸弹袭击身亡",
      "url": "https://www.ftchinese.com/story/001108510",
      "source": "ftchinese.com",
      "published": 1766419200
    },
    {
      "id": "a357c937e2f6",
      "title": "开源模型可能刺破人工智能估值泡沫",
      "url": "https://www.ftchinese.com/story/001108509",
      "source": "ftchinese.com",
      "published": 1766419200
    },
    {
      "id": "8d71a6582d0e",
      "title": "德语媒体：北京给德国外长的一堂“历史课”",
      "url": "https://www.dw.com/zh/德语媒体：北京给德国外长的一堂-历史课/a-75270510?maca=chi-rss-chi-all-1127-rdf",
      "source": "dw.com",
      "published": 1766414580
    },
    {
      "id": "db7efa130765",
      "title": "技术工人短缺：为何富裕国家要遏制劳工移民",
      "url": "https://www.dw.com/zh/技术工人短缺：为何富裕国家要遏制劳工移民/a-75269529?maca=chi-rss-chi-all-1127-rdf",
      "source": "dw.com",
      "published": 1766410020
    },
    {
      "id": "335d7d50f834",
      "title": "欧盟谴责中国对欧洲乳制品加征关税“毫无道理”：欧中关系“非常负面的一次升级”",
      "url": "https://www.rfi.fr/cn/%E4%B8%AD%E5%9B%BD/20251222-%E6%AC%A7%E7%9B%9F%E8%B0%B4%E8%B4%A3%E4%B8%AD%E5%9B%BD%E5%AF%B9%E6%AC%A7%E6%B4%B2%E4%B9%B3%E5%88%B6%E5%93%81%E5%8A%A0%E5%BE%81%E5%85%B3%E7%A8%8E-%E6%AF%AB%E6%97%A0%E9%81%93%E7%90%86",
      "source": "rfi.fr",
      "published": 1766409136
    },
    {
      "id": "708383cabc01",
      "title": "德国财长批评德铁采购中国电动巴士 呼吁“爱国主义”",
      "url": "https://www.dw.com/zh/德国财长批评德铁采购中国电动巴士-呼吁-爱国主义/a-75266347?maca=chi-rss-chi-all-1127-rdf",
      "source": "dw.com",
      "published": 1766403720
    },
    {
      "id": "c98f733034db",
      "title": "一名俄罗斯中将在汽车炸弹袭击中丧生",
      "url": "https://www.dw.com/zh/一名俄罗斯中将在汽车炸弹袭击中丧生/a-75264894?maca=chi-rss-chi-all-1127-rdf",
      "source": "dw.com",
      "published": 1766403660
    },
    {
      "id": "100a83500d59",
      "title": "對美國用戶來說，TikTok出售後會變得更安全但卻可有可無嗎？",
      "url": "https://www.bbc.com/zhongwen/articles/cvgr0m9xdxko/trad?at_medium=RSS&at_campaign=rss",
      "source": "bbc.com",
      "published": 1766394928
    },
    {
      "id": "0454942d031d",
      "title": "停用減肥針之後會發生什麼，兩個體驗者的不同故事",
      "url": "https://www.bbc.com/zhongwen/articles/cwyl01zeqgjo/trad?at_medium=RSS&at_campaign=rss",
      "source": "bbc.com",
      "published": 1766379997
    },
    {
      "id": "6564df058907",
      "title": "緬甸叛軍控制區平民面臨政府軍空襲與一場被指虛假的選舉",
      "url": "https://www.bbc.com/zhongwen/articles/c1kp17xjj1mo/trad?at_medium=RSS&at_campaign=rss",
      "source": "bbc.com",
      "published": 1766378621
    },
    {
      "id": "a69c9d4e39a7",
      "title": "今日中国，我们所知？《观点》专栏作家解析习近平威权整顿的隐忧",
      "url": "https://www.rfi.fr/cn/%E4%B8%AD%E5%9B%BD/20251221-%E4%BB%8A%E6%97%A5%E4%B8%AD%E5%9B%BD%EF%BC%8C%E6%88%91%E4%BB%AC%E6%89%80%E7%9F%A5-%E8%A7%82%E7%82%B9-%E4%B8%93%E6%A0%8F%E4%BD%9C%E5%AE%B6%E8%A7%A3%E6%9E%90%E4%B9%A0%E8%BF%91%E5%B9%B3%E5%A8%81%E6%9D%83%E6%95%B4%E9%A1%BF%E7%9A%84%E9%9A%90%E5%BF%A7",
      "source": "rfi.fr",
      "published": 1766360355
    },
    {
      "id": "fb705c3888de",
      "title": "墙外文摘：中日两国的冲突表演会玩过头吗？",
      "url": "https://www.dw.com/zh/墙外文摘：中日两国的冲突表演会玩过头吗？/a-75259018?maca=chi-rss-chi-all-1127-rdf",
      "source": "dw.com",
      "published": 1766336340
    },
    {
      "id": "854287e1aa18",
      "title": "竞投内斗击退日上免税行 中免拿下上海机场免税店",
      "url": "https://www.ftchinese.com/story/001108497",
      "source": "ftchinese.com",
      "published": 1766332800
    },
    {
      "id": "798f7407053f",
      "title": "为什么中国宏观经济政策的力度不升反降？",
      "url": "https://www.ftchinese.com/story/001108502",
      "source": "ftchinese.com",
      "published": 1766332800
    },
    {
      "id": "14761a01cc55",
      "title": "一周世界舆论聚焦：韩国靠近中国与美国在中日间平衡",
      "url": "https://www.ftchinese.com/story/001108501",
      "source": "ftchinese.com",
      "published": 1766332800
    },
    {
      "id": "8c288793f4a3",
      "title": "FT社评：欧洲需要决心与行动",
      "url": "https://www.ftchinese.com/story/001108499",
      "source": "ftchinese.com",
      "published": 1766332800
    },
    {
      "id": "61bd8504e091",
      "title": "角色颠倒：退缩的法国让德国措手不及",
      "url": "https://www.ftchinese.com/story/001108498",
      "source": "ftchinese.com",
      "published": 1766332800
    },
    {
      "id": "e17de875e025",
      "title": "市场重科技轻饮食 巴奴上市有压力",
      "url": "https://www.ftchinese.com/story/001108496",
      "source": "ftchinese.com",
      "published": 1766332800
    },
    {
      "id": "424bfb48e28d",
      "title": "美国再次扣押运载委内瑞拉石油的油轮",
      "url": "https://www.ftchinese.com/story/001108495",
      "source": "ftchinese.com",
      "published": 1766332800
    },
    {
      "id": "093361f0dd3d",
      "title": "泰柬边境冲突：逾50万平民流离失所",
      "url": "https://www.dw.com/zh/泰柬边境冲突：逾50万平民流离失所/a-75258669?maca=chi-rss-chi-all-1127-rdf",
      "source": "dw.com",
      "published": 1766330340
    },
    {
      "id": "3b60a526ecc9",
      "title": "德国工程师写下历史：首位轮椅使用者圆梦太空",
      "url": "https://www.dw.com/zh/德国工程师写下历史：首位轮椅使用者圆梦太空/a-75257504?maca=chi-rss-chi-news-3224-rdf",
      "source": "dw.com",
      "published": 1766316060
    },
    {
      "id": "e927e31bbea2",
      "title": "德国工程师写下历史：首位轮椅使用者圆梦太空",
      "url": "https://www.dw.com/zh/德国工程师写下历史：首位轮椅使用者圆梦太空/a-75257504?maca=chi-rss-chi-all-1127-rdf",
      "source": "dw.com",
      "published": 1766316060
    },
    {
      "id": "1f990cb145ed",
      "title": "俄加入迈阿密会谈 否认将举行美俄乌三方会谈",
      "url": "https://www.dw.com/zh/俄加入迈阿密会谈-否认将举行美俄乌三方会谈/a-75257481?maca=chi-rss-chi-all-1127-rdf",
      "source": "dw.com",
      "published": 1766315220
    },
    {
      "id": "ddc9abbe6afe",
      "title": "澳大利亞曾是控槍典範，但邦迪海灘事件揭露更複雜的現實",
      "url": "https://www.bbc.com/zhongwen/articles/c2k4y9k3323o/trad?at_medium=RSS&at_campaign=rss",
      "source": "bbc.com",
      "published": 1766309753
    },
    {
      "id": "a85f84fdc5ab",
      "title": "德国汽车重镇为何面临财政危机？",
      "url": "https://www.dw.com/zh/德国汽车重镇为何面临财政危机？/a-75188379?maca=chi-rss-chi-all-1127-rdf",
      "source": "dw.com",
      "published": 1766305140
    },
    {
      "id": "56bbd9a76d30",
      "title": "黎智英：這位挑戰中國底線的億萬富翁，付上了自由的代價",
      "url": "https://www.bbc.com/zhongwen/articles/cp8zpyrvmm4o/trad?at_medium=RSS&at_campaign=rss",
      "source": "bbc.com",
      "published": 1766300301
    },
    {
      "id": "5577573fb3a3",
      "title": "爱泼斯坦案文档公布 仍大面积涂黑",
      "url": "https://www.dw.com/zh/爱泼斯坦案文档公布-仍大面积涂黑/a-75253692?maca=chi-rss-chi-news-3224-rdf",
      "source": "dw.com",
      "published": 1766243100
    },
    {
      "id": "8751fedf772f",
      "title": "台灣鬧市隨機襲擊4死11傷：27歲男子台北車站一帶擲煙霧彈及亂刀傷人",
      "url": "https://www.bbc.com/zhongwen/articles/crmdpxgz7nno/trad?at_medium=RSS&at_campaign=rss",
      "source": "bbc.com",
      "published": 1766217137
    },
    {
      "id": "9a5ad53d949a",
      "title": "27歲男子台北車站隨機斬人  至少四死九傷",
      "url": "https://www.bbc.com/zhongwen/articles/czdg27n96gyo/trad?at_medium=RSS&at_campaign=rss",
      "source": "bbc.com",
      "published": 1766166661
    },
    {
      "id": "32a7c9c055b8",
      "title": "德语媒体：中国芯片制造技术取得重大突破？",
      "url": "https://www.dw.com/zh/德语媒体：中国芯片制造技术取得重大突破？/a-75246274?maca=chi-rss-chi-all-1127-rdf",
      "source": "dw.com",
      "published": 1766157720
    },
    {
      "id": "6ed136174975",
      "title": "詳解美國破紀錄對台軍售：價值111億美元的非對稱式防禦藍圖",
      "url": "https://www.bbc.com/zhongwen/articles/c30j26p3l9no/trad?at_medium=RSS&at_campaign=rss",
      "source": "bbc.com",
      "published": 1766138198
    },
    {
      "id": "f0cd2c0f569c",
      "title": "客座评论：西方国家的“软外交”",
      "url": "https://www.dw.com/zh/客座评论：西方国家的-软外交/a-75224733?maca=chi-rss-chi-all-1127-rdf",
      "source": "dw.com",
      "published": 1766137320
    },
    {
      "id": "92d689159cf7",
      "title": "烏克蘭打造國產武器的秘密工廠：「不靠美國或中國零部件」",
      "url": "https://www.bbc.com/zhongwen/articles/cpq4p5jrxdjo/trad?at_medium=RSS&at_campaign=rss",
      "source": "bbc.com",
      "published": 1766134850
    },
    {
      "id": "a8661eaac7d7",
      "title": "性生活不再需要另一半？中國避孕套和情趣用品「一冷一熱」背後的原因",
      "url": "https://www.bbc.com/zhongwen/articles/c5yjv3nym4ro/trad?at_medium=RSS&at_campaign=rss",
      "source": "bbc.com",
      "published": 1766125564
    },
    {
      "id": "925069698f24",
      "title": "使用被冻结俄罗斯资产为乌克兰提供赔偿贷款？欧盟峰会即将做出决定",
      "url": "https://www.dw.com/zh/使用被冻结俄罗斯资产为乌克兰提供赔偿贷款？欧盟峰会即将做出决定/a-75224957?maca=chi-rss-chi-all-1127-rdf",
      "source": "dw.com",
      "published": 1766068680
    },
    {
      "id": "e66c2d32da00",
      "title": "德语媒体：\"感谢特朗普，习近平成了2025年最大赢家!\"",
      "url": "https://www.dw.com/zh/德语媒体：-感谢特朗普，习近平成了2025年最大赢家/a-75224675?maca=chi-rss-chi-all-1127-rdf",
      "source": "dw.com",
      "published": 1766068620
    },
    {
      "id": "dc9184ff84eb",
      "title": "格陵蘭母親尋回孩子的鬥爭：我的寶寶出生便被丹麥政府帶走",
      "url": "https://www.bbc.com/zhongwen/articles/c93w7z135yko/trad?at_medium=RSS&at_campaign=rss",
      "source": "bbc.com",
      "published": 1766065754
    },
    {
      "id": "0fe1e02ccc68",
      "title": "高市早苗希望與中國「持續坦誠對話」，態度是否出現軟化？",
      "url": "https://www.bbc.com/zhongwen/articles/cj387gyk1r7o/trad?at_medium=RSS&at_campaign=rss",
      "source": "bbc.com",
      "published": 1766043083
    },
    {
      "id": "1a8d9acdff81",
      "title": "哪個世代的英國人最受孤獨所困？答案可能出乎你意料",
      "url": "https://www.bbc.com/zhongwen/articles/cpvdx34r0zpo/trad?at_medium=RSS&at_campaign=rss",
      "source": "bbc.com",
      "published": 1766036057
    },
    {
      "id": "633baaeebcc9",
      "title": "宇宙中的恆星正走向枯竭嗎",
      "url": "https://www.bbc.com/zhongwen/articles/ce3z5lnnqd5o/trad?at_medium=RSS&at_campaign=rss",
      "source": "bbc.com",
      "published": 1766017189
    },
    {
      "id": "c9fc3b8f6d28",
      "title": "德语媒体：在发展援助领域 中国正在取代美国",
      "url": "https://www.dw.com/zh/德语媒体：在发展援助领域-中国正在取代美国/a-75204816?maca=chi-rss-chi-all-1127-rdf",
      "source": "dw.com",
      "published": 1765981140
    },
    {
      "id": "122dae7ecdbd",
      "title": "悉尼海灘槍擊疑與「伊斯蘭國」有關  畫面顯示多人試圖阻止兇手",
      "url": "https://www.bbc.com/zhongwen/articles/cx2ew8yxlqgo/trad?at_medium=RSS&at_campaign=rss",
      "source": "bbc.com",
      "published": 1765959502
    },
    {
      "id": "e2aff29c7ea6",
      "title": "專訪《左撇子女孩》鄒時擎：女生成長不需要這麼痛苦",
      "url": "https://www.dw.com/zh/專訪《左撇子女孩》鄒時擎：女生成長不需要這麼痛苦/a-75177386?maca=chi-rss-chi-all-1127-rdf",
      "source": "dw.com",
      "published": 1765950780
    },
    {
      "id": "c743d948e627",
      "title": "德语媒体：香港报人黎智英面临终身监禁",
      "url": "https://www.dw.com/zh/德语媒体：香港报人黎智英面临终身监禁/a-75187676?maca=chi-rss-chi-all-1127-rdf",
      "source": "dw.com",
      "published": 1765897020
    },
    {
      "id": "7c9aa33e02ab",
      "title": "「MAGA」人群如何走向分裂？這對特朗普意味著什麼？",
      "url": "https://www.bbc.com/zhongwen/articles/cpd6854llzno/trad?at_medium=RSS&at_campaign=rss",
      "source": "bbc.com",
      "published": 1765878948
    },
    {
      "id": "bd06c8a8c797",
      "title": "芬蘭小姐「拉眼角」照片掀起的種族議題風波",
      "url": "https://www.bbc.com/zhongwen/articles/cd0k33ynv2no/trad?at_medium=RSS&at_campaign=rss",
      "source": "bbc.com",
      "published": 1765876979
    },
    {
      "id": "c0254daa1fb1",
      "title": "“润欧”的尽头是德国？中国走线人的自由与幻梦",
      "url": "https://www.dw.com/zh/润欧-的尽头是德国？中国走线人的自由与幻梦/a-75157422?maca=chi-rss-chi-all-1127-rdf",
      "source": "dw.com",
      "published": 1765855080
    },
    {
      "id": "9fb2aaf9e12c",
      "title": "觀察：特朗普的新安全戰略顯示美國外交政策的重大轉變",
      "url": "https://www.bbc.com/zhongwen/articles/cwywgl1p95wo/trad?at_medium=RSS&at_campaign=rss",
      "source": "bbc.com",
      "published": 1765844238
    },
    {
      "id": "3a466452e72b",
      "title": "国际社会强烈回应黎智英被判罪成",
      "url": "https://www.dw.com/zh/国际社会强烈回应黎智英被判罪成/a-75167109?maca=chi-rss-chi-all-1127-rdf",
      "source": "dw.com",
      "published": 1765813620
    },
    {
      "id": "590e1e93a41c",
      "title": "俄罗斯宣布德国之声为“不受欢迎组织”",
      "url": "https://www.dw.com/zh/俄罗斯宣布德国之声为-不受欢迎组织/a-75159666?maca=chi-rss-chi-all-1127-rdf",
      "source": "dw.com",
      "published": 1765796280
    },
    {
      "id": "a88c11331fac",
      "title": "「不枉此生的新聞歲月」：《蘋果日報》前記者談黎智英",
      "url": "https://www.bbc.com/zhongwen/articles/cd740xw1ne7o/trad?at_medium=RSS&at_campaign=rss",
      "source": "bbc.com",
      "published": 1765787039
    },
    {
      "id": "f236eced2971",
      "title": "巴黎卢浮宫漏水 数百本历史书籍受损",
      "url": "https://www.dw.com/zh/巴黎卢浮宫漏水-数百本历史书籍受损/a-75067522?maca=chi-rss-chi-all-1127-rdf",
      "source": "dw.com",
      "published": 1765698420
    },
    {
      "id": "1298f0ef2dd5",
      "title": "捐精者的精子恐导致近200幼童患癌",
      "url": "https://www.dw.com/zh/捐精者的精子恐导致近200幼童患癌/a-75094855?maca=chi-rss-chi-all-1127-rdf",
      "source": "dw.com",
      "published": 1765698420
    },
    {
      "id": "1e9a4335c484",
      "title": "搜救犬牵起台湾与德国之间的情谊",
      "url": "https://www.dw.com/zh/搜救犬牵起台湾与德国之间的情谊/a-75111890?maca=chi-rss-chi-all-1127-rdf",
      "source": "dw.com",
      "published": 1765698300
    },
    {
      "id": "282368223494",
      "title": "Reddit状告澳洲禁止儿童使用社媒法侵犯自由",
      "url": "https://www.dw.com/zh/reddit状告澳洲禁止儿童使用社媒法侵犯自由/a-75131360?maca=chi-rss-chi-news-3224-rdf",
      "source": "dw.com",
      "published": 1765547040
    },
    {
      "id": "95f4b7580dc8",
      "title": "二战遗留炸弹引爆 冲击波损坏多栋房屋",
      "url": "https://www.dw.com/zh/二战遗留炸弹引爆-冲击波损坏多栋房屋/a-75130429?maca=chi-rss-chi-news-3224-rdf",
      "source": "dw.com",
      "published": 1765543560
    },
    {
      "id": "79f6774a4d43",
      "title": "特朗普雖解禁H200晶片，中國「算力自主」策略下輝達尚難言慶祝",
      "url": "https://www.bbc.com/zhongwen/articles/cdj88l4kw9xo/trad?at_medium=RSS&at_campaign=rss",
      "source": "bbc.com",
      "published": 1765528890
    },
    {
      "id": "64db82397579",
      "title": "「自己的子宮自己做主」：台灣《人工生殖法》修法擬納入單身女性、女同志",
      "url": "https://www.bbc.com/zhongwen/articles/cj4qqx5wpj1o/trad?at_medium=RSS&at_campaign=rss",
      "source": "bbc.com",
      "published": 1765516819
    },
    {
      "id": "0c2f60fcb7b3",
      "title": "如何保護自己免受即將「席捲全球」的變異流感病毒感染？",
      "url": "https://www.bbc.com/zhongwen/articles/c9w7751vjk4o/trad?at_medium=RSS&at_campaign=rss",
      "source": "bbc.com",
      "published": 1765509804
    },
    {
      "id": "2999fba51442",
      "title": "拆解宏福苑億元大維修時間線，屢遭質疑的香港圍標現象如何形成？",
      "url": "https://www.bbc.com/zhongwen/articles/cjrj0320pdgo/trad?at_medium=RSS&at_campaign=rss",
      "source": "bbc.com",
      "published": 1765498927
    },
    {
      "id": "a4f122f38ba5",
      "title": "中日外交僵局難解，持續拉鋸是否成為新常態？",
      "url": "https://www.bbc.com/zhongwen/articles/cm20ep54395o/trad?at_medium=RSS&at_campaign=rss",
      "source": "bbc.com",
      "published": 1765452604
    },
    {
      "id": "b1e848f8e40d",
      "title": "委內瑞拉是否已被其兩大盟友——中俄拋棄？",
      "url": "https://www.bbc.com/zhongwen/articles/cjezknjxnnqo/trad?at_medium=RSS&at_campaign=rss",
      "source": "bbc.com",
      "published": 1765430387
    },
    {
      "id": "b2c6c356e8f1",
      "title": "德国外长瓦德富尔访问中国：寻找稀土之旅",
      "url": "https://www.dw.com/zh/德国外长瓦德富尔访问中国：寻找稀土之旅/a-75089896?maca=chi-rss-chi-all-1127-rdf",
      "source": "dw.com",
      "published": 1765368300
    },
    {
      "id": "169de14c08fc",
      "title": "川普為輝達AI晶片銷中國開綠燈 北京買單嗎?",
      "url": "https://www.dw.com/zh/川普為輝達ai晶片銷中國開綠燈-北京買單嗎/a-75072557?maca=chi-rss-chi-all-1127-rdf",
      "source": "dw.com",
      "published": 1765359300
    },
    {
      "id": "2e9ddc4a26e0",
      "title": "全球首例 澳洲16歲以下青少年「社群禁令」生效",
      "url": "https://www.dw.com/zh/全球首例-澳洲16歲以下青少年「社群禁令」生效/a-75085767?maca=chi-rss-chi-all-1127-rdf",
      "source": "dw.com",
      "published": 1765358340
    },
    {
      "id": "95a51a4d4bf8",
      "title": "「她逃不了，哪裡也去不了」：香港宏福苑大火中罹難和倖存外傭",
      "url": "https://www.bbc.com/zhongwen/articles/cd6x7ylynv0o/trad?at_medium=RSS&at_campaign=rss",
      "source": "bbc.com",
      "published": 1765354651
    },
    {
      "id": "a1d624b20b03",
      "title": "欧盟对谷歌AI展开反垄断调查",
      "url": "https://www.dw.com/zh/欧盟对谷歌ai展开反垄断调查/a-75074965?maca=chi-rss-chi-all-1127-rdf",
      "source": "dw.com",
      "published": 1765279500
    },
    {
      "id": "b5af0cbe1f90",
      "title": "全球今年共有67名记者因工作丧生",
      "url": "https://www.dw.com/zh/全球今年共有67名记者因工作丧生/a-75074141?maca=chi-rss-chi-all-1127-rdf",
      "source": "dw.com",
      "published": 1765274520
    },
    {
      "id": "e9a6f8428583",
      "title": "中國短劇流水線揭秘：寬鬆審核下的速度與豪賭",
      "url": "https://www.bbc.com/zhongwen/articles/ckgzn10qg22o/trad?at_medium=RSS&at_campaign=rss",
      "source": "bbc.com",
      "published": 1765239553
    },
    {
      "id": "df9e422b3733",
      "title": "特朗普簽《台灣保證實施法案》：對台「制度化」保障，還是對北京的談判籌碼？",
      "url": "https://www.bbc.com/zhongwen/articles/clydrkrzn30o/trad?at_medium=RSS&at_campaign=rss",
      "source": "bbc.com",
      "published": 1765174365
    },
    {
      "id": "8633705ee7bb",
      "title": "阿伦特在中国：思考作为精神的家园",
      "url": "https://www.dw.com/zh/阿伦特在中国：思考作为精神的家园/a-75033730?maca=chi-rss-chi-all-1127-rdf",
      "source": "dw.com",
      "published": 1765095900
    },
    {
      "id": "9fadb63c40b6",
      "title": "为什么基辅的学生仍然说俄语？",
      "url": "https://www.dw.com/zh/为什么基辅的学生仍然说俄语？/a-74972352?maca=chi-rss-chi-all-1127-rdf",
      "source": "dw.com",
      "published": 1765095840
    },
    {
      "id": "c358ef676a4a",
      "title": "白宫推出新网站羞辱记者 专家警告危及新闻自由",
      "url": "https://www.dw.com/zh/白宫推出新网站羞辱记者-专家警告危及新闻自由/a-75046551?maca=chi-rss-chi-all-1127-rdf",
      "source": "dw.com",
      "published": 1765027140
    },
    {
      "id": "695ccdb6aaa2",
      "title": "大国贸易战夹缝中的商人该如何生存",
      "url": "https://www.dw.com/zh/大国贸易战夹缝中的商人该如何生存/a-75019116?maca=chi-rss-chi-all-1127-rdf",
      "source": "dw.com",
      "published": 1764857340
    },
    {
      "id": "7f014efd7215",
      "title": "高市早苗热：手袋卖到断货！誓言成日本年度流行语",
      "url": "https://www.dw.com/zh/高市早苗热：手袋卖到断货！誓言成日本年度流行语/a-75016119?maca=chi-rss-chi-all-1127-rdf",
      "source": "dw.com",
      "published": 1764848940
    },
    {
      "id": "db0b78467eec",
      "title": "觀察：美俄莫斯科會談揭示了普京怎樣的心態",
      "url": "https://www.bbc.com/zhongwen/articles/crrk7kee9x5o/trad?at_medium=RSS&at_campaign=rss",
      "source": "bbc.com",
      "published": 1764819674
    },
    {
      "id": "5ecbb9b11db5",
      "title": "台灣的對美右翼媒體攻勢：賴清德與蕭美琴的外交新策略能成功嗎？",
      "url": "https://www.bbc.com/zhongwen/articles/c5yq53qpj6wo/trad?at_medium=RSS&at_campaign=rss",
      "source": "bbc.com",
      "published": 1764753342
    },
    {
      "id": "d846bd7c176e",
      "title": "滨崎步在上海开“空椅子演唱会” 网民：丟脸的是中国",
      "url": "https://www.dw.com/zh/滨崎步在上海开-空椅子演唱会-网民：丟脸的是中国/a-74984178?maca=chi-rss-chi-all-1127-rdf",
      "source": "dw.com",
      "published": 1764679980
    },
    {
      "id": "ee934753c5ea",
      "title": "DW Access 常见问题解答",
      "url": "https://www.dw.com/zh/dw-access-常见问题解答/a-74968206?maca=chi-rss-chi-all-1127-rdf",
      "source": "dw.com",
      "published": 1764592380
    },
    {
      "id": "91b1f6e5908b",
      "title": "香港火灾死亡人数上升至146人 当局下令加强安全审查",
      "url": "https://www.dw.com/zh/香港火灾死亡人数上升至146人-当局下令加强安全审查/a-74956418?maca=chi-rss-chi-news-3224-rdf",
      "source": "dw.com",
      "published": 1764499380
    },
    {
      "id": "736fd592558f",
      "title": "半世纪后再登月 德国宇航员将飞往月球",
      "url": "https://www.dw.com/zh/半世纪后再登月-德国宇航员将飞往月球/a-74944653?maca=chi-rss-chi-all-1127-rdf",
      "source": "dw.com",
      "published": 1764490620
    },
    {
      "id": "74b8ee2009e2",
      "title": "香港宏福苑大火 竹制棚架惹的祸？",
      "url": "https://www.dw.com/zh/香港宏福苑大火-竹制棚架惹的祸？/a-74924017?maca=chi-rss-chi-news-3224-rdf",
      "source": "dw.com",
      "published": 1764250620
    },
    {
      "id": "09fce1e48216",
      "title": "香港宏福苑大火：外牆施工材料易燃 工程公司3人被捕",
      "url": "https://www.dw.com/zh/香港宏福苑大火：外牆施工材料易燃-工程公司3人被捕/a-74914548?maca=chi-rss-chi-news-3224-rdf",
      "source": "dw.com",
      "published": 1764218580
    }
  ],
  "build_id": 1766511691
}