{
  "updated": 1756924857,
  "items": [
    {
      "id": "4ecb3a37477d",
      "title": "歐、日、印度8月景氣好轉",
      "url": "https://money.udn.com/money/story/5599/8982166",
      "source": "money.udn.com",
      "published": 1756924303
    },
    {
      "id": "4d200a813847",
      "title": "美購物旺季 消費動能看淡",
      "url": "https://money.udn.com/money/story/10511/8982176",
      "source": "money.udn.com",
      "published": 1756924269
    },
    {
      "id": "3121e7c2e8f7",
      "title": "俄烏和談無進度？川普：很快與普亭通話",
      "url": "https://money.udn.com/money/story/5599/8982372",
      "source": "money.udn.com",
      "published": 1756924243
    },
    {
      "id": "12b062dc6cc5",
      "title": "美反托辣斯案救濟措施裁決 Google 不必賣 Chrome 事業",
      "url": "https://money.udn.com/money/story/123398/8982175",
      "source": "money.udn.com",
      "published": 1756924238
    },
    {
      "id": "752328f3d266",
      "title": "歐洲推新電動車 叫陣陸廠",
      "url": "https://money.udn.com/money/story/5599/8982171",
      "source": "money.udn.com",
      "published": 1756924165
    },
    {
      "id": "730858789f22",
      "title": "Google 旗下 TPU 事業 值9,000億美元",
      "url": "https://money.udn.com/money/story/123398/8982137",
      "source": "money.udn.com",
      "published": 1756924089
    },
    {
      "id": "b0c179d52d32",
      "title": "軟體巨擘 Salesforce 倚重 AI  大砍人力",
      "url": "https://money.udn.com/money/story/123398/8982136",
      "source": "money.udn.com",
      "published": 1756924058
    },
    {
      "id": "2140d471dd7f",
      "title": "1分鐘看世界／泰國預期原產地證明需求激增 將成立專責小組處理",
      "url": "https://money.udn.com/money/story/5599/8982185",
      "source": "money.udn.com",
      "published": 1756924006
    },
    {
      "id": "c00dd3b81fc7",
      "title": "中俄朝伊结盟北京刚落幕 30国“志愿者联盟”巴黎会议即登场",
      "url": "https://www.rfi.fr/cn/%E4%B8%93%E6%A0%8F%E6%A3%80%E7%B4%A2/%E8%A6%81%E9%97%BB%E5%88%86%E6%9E%90/20250903-%E4%B8%AD%E4%BF%84%E6%9C%9D%E4%BC%8A%E7%BB%93%E7%9B%9F%E5%8C%97%E4%BA%AC%E8%90%BD%E5%B9%95-30%E5%9B%BD-%E5%BF%97%E6%84%BF%E8%80%85%E8%81%94%E7%9B%9F-%E4%BC%9A%E8%AE%AE%E5%B7%B4%E9%BB%8E%E7%99%BB%E5%9C%BA",
      "source": "rfi.fr",
      "published": 1756923970
    },
    {
      "id": "8f58e6df8adb",
      "title": "終結俄烏戰爭　蒲亭：看見隧道盡頭一點光亮",
      "url": "https://money.udn.com/money/story/10511/8982370",
      "source": "money.udn.com",
      "published": 1756923751
    },
    {
      "id": "3b9b25e5cf20",
      "title": "管中閔：政府不提抗戰勝利與台灣光復 因無真正的台灣意識",
      "url": "https://udn.com/news/story/10930/8982328",
      "source": "udn.com",
      "published": 1756920198
    },
    {
      "id": "afa43eca6db3",
      "title": "美國星巴克也導入AI　員工少跑倉庫、多與顧客交流",
      "url": "https://money.udn.com/money/story/5599/8982356",
      "source": "money.udn.com",
      "published": 1756920080
    },
    {
      "id": "7a636cf1ecc1",
      "title": "投資人靜待美國就業數據出爐　歐股收漲",
      "url": "https://money.udn.com/money/story/5599/8982350",
      "source": "money.udn.com",
      "published": 1756918468
    },
    {
      "id": "b37734936e34",
      "title": "數位黃金最快明年問世 顛覆9,000億美元市場",
      "url": "https://money.udn.com/money/story/5599/8982181",
      "source": "money.udn.com",
      "published": 1756918283
    },
    {
      "id": "8610fd608a90",
      "title": "金價衝破3,600美元",
      "url": "https://money.udn.com/money/story/5599/8982182",
      "source": "money.udn.com",
      "published": 1756918249
    },
    {
      "id": "357d2fe029dc",
      "title": "川普促關稅訴訟「快速審理」 將向最高法院爭取推翻先前判決",
      "url": "https://money.udn.com/money/story/5599/8982187",
      "source": "money.udn.com",
      "published": 1756917569
    },
    {
      "id": "e8bb3dd0f31c",
      "title": "美、日30年期殖利率衝高…長債跌勢「斷路器」遙不可及",
      "url": "https://money.udn.com/money/story/5599/8982188",
      "source": "money.udn.com",
      "published": 1756917422
    },
    {
      "id": "a3150077be95",
      "title": "美財長面談Fed主席人選",
      "url": "https://money.udn.com/money/story/5599/8982189",
      "source": "money.udn.com",
      "published": 1756917387
    },
    {
      "id": "e60fd45a9d25",
      "title": "路燈、教學電費補助取消 白委：政院出奧步",
      "url": "https://udn.com/news/story/124582/8982236",
      "source": "udn.com",
      "published": 1756916842
    },
    {
      "id": "cf95f651e537",
      "title": "暗批中共九三閱兵 賴總統：台灣不拿槍桿子紀念和平",
      "url": "https://udn.com/news/story/10930/8982210",
      "source": "udn.com",
      "published": 1756916754
    },
    {
      "id": "2e98fa1441b0",
      "title": "蘋果AI人才出走 還沒止血",
      "url": "https://money.udn.com/money/story/5599/8982230",
      "source": "money.udn.com",
      "published": 1756916744
    },
    {
      "id": "62e286c0af42",
      "title": "三星追台積 南韓政府扮神隊友 助廠商降低成本",
      "url": "https://money.udn.com/money/story/5599/8982222",
      "source": "money.udn.com",
      "published": 1756916639
    },
    {
      "id": "9ca50c758db6",
      "title": "賴清德：人事改組完成 目標2026地方大選",
      "url": "https://udn.com/news/story/6656/8982281",
      "source": "udn.com",
      "published": 1756916595
    },
    {
      "id": "f7f4a5925038",
      "title": "賴總統夜宴綠委 柯建銘發言不多",
      "url": "https://udn.com/news/story/6656/8982283",
      "source": "udn.com",
      "published": 1756916585
    },
    {
      "id": "b9a5e9d3ca67",
      "title": "專心市政 盧秀燕重申不選黨主席",
      "url": "https://udn.com/news/story/6656/8982284",
      "source": "udn.com",
      "published": 1756916584
    },
    {
      "id": "f12ccffb689b",
      "title": "卓揆怨媒宣費被刪 藍譏「養黨媒」",
      "url": "https://udn.com/news/story/6656/8982286",
      "source": "udn.com",
      "published": 1756916584
    },
    {
      "id": "549ce52e0459",
      "title": "新聞幕後／賴、柯有共識 交棒時間仍僵持",
      "url": "https://udn.com/news/story/6656/8982285",
      "source": "udn.com",
      "published": 1756916584
    },
    {
      "id": "2e0eb73c5b9a",
      "title": "北韓疑對身心障礙者進行醫學實驗　聯合國關注",
      "url": "https://money.udn.com/money/story/5599/8982336",
      "source": "money.udn.com",
      "published": 1756916121
    },
    {
      "id": "da24f1b98654",
      "title": "外媒曝 陸南海鑽油 侵我專屬經濟區",
      "url": "https://udn.com/news/story/124588/8982270",
      "source": "udn.com",
      "published": 1756916002
    },
    {
      "id": "b2095452c0c5",
      "title": "朝野譴責 藍：陸違法探勘試我底線",
      "url": "https://udn.com/news/story/124588/8982295",
      "source": "udn.com",
      "published": 1756915930
    },
    {
      "id": "1887686b9057",
      "title": "專家：EEZ主權要靠聲索國談出來 兩岸無管道此事就難談",
      "url": "https://udn.com/news/story/124588/8982294",
      "source": "udn.com",
      "published": 1756915829
    },
    {
      "id": "a8845f6c4a1c",
      "title": "明年總預算出爐 中央水電預算暴增12.9億挨批",
      "url": "https://udn.com/news/story/6656/8982302",
      "source": "udn.com",
      "published": 1756915625
    },
    {
      "id": "e2cc6bbeceb7",
      "title": "台日執政黨2+2會談 擴大為4+4",
      "url": "https://udn.com/news/story/6656/8982304",
      "source": "udn.com",
      "published": 1756915426
    },
    {
      "id": "aab92e1e101f",
      "title": "歷史上的今天／1966年陽明山發現地熱 經部籌畫開採",
      "url": "https://udn.com/news/story/7314/8980221",
      "source": "udn.com",
      "published": 1756915200
    },
    {
      "id": "5fde9bd9075a",
      "title": "川普政策變數多 美國企業職缺下滑至近一年低點",
      "url": "https://money.udn.com/money/story/5599/8982309",
      "source": "money.udn.com",
      "published": 1756915178
    },
    {
      "id": "765f2414527b",
      "title": "气候正义: 印尼居民状告瑞士水泥巨头Holcim",
      "url": "https://www.rfi.fr/cn/%E4%B8%93%E6%A0%8F%E6%A3%80%E7%B4%A2/%E7%8E%AF%E4%BF%9D%E5%A4%A9%E5%9C%B0/20250903-%E6%B0%94%E5%80%99%E6%AD%A3%E4%B9%89-%E5%8D%B0%E5%B0%BC%E5%B1%85%E6%B0%91%E7%8A%B6%E5%91%8A%E7%91%9E%E5%A3%AB%E6%B0%B4%E6%B3%A5%E5%B7%A8%E5%A4%B4holcim",
      "source": "rfi.fr",
      "published": 1756914649
    },
    {
      "id": "61d4445f3cc6",
      "title": "普京指特朗普称中俄朝密谋反美是幽默 强调“单极世界必须不复存在”",
      "url": "https://www.rfi.fr/cn/%E5%9B%BD%E9%99%85/20250903-%E6%99%AE%E4%BA%AC%E6%8C%87%E7%89%B9%E6%9C%97%E6%99%AE%E7%A7%B0%E4%B8%AD%E4%BF%84%E6%9C%9D%E5%AF%86%E8%B0%8B%E5%8F%8D%E7%BE%8E%E6%98%AF%E5%B9%BD%E9%BB%98-%E5%8D%95%E6%9E%81%E4%B8%96%E7%95%8C%E5%BF%85%E9%A1%BB%E4%B8%8D%E5%A4%8D%E5%AD%98%E5%9C%A8",
      "source": "rfi.fr",
      "published": 1756914187
    },
    {
      "id": "415163240027",
      "title": "亚洲战场终战80周年纪念：和平口号背后的紧张关系",
      "url": "https://www.rfi.fr/cn/%E4%B8%93%E6%A0%8F%E6%A3%80%E7%B4%A2/%E8%A6%81%E9%97%BB%E8%A7%A3%E8%AF%B4/20250903-%E4%BA%9A%E6%B4%B2%E6%88%98%E5%9C%BA%E7%BB%88%E6%88%9880%E5%91%A8%E5%B9%B4%E7%BA%AA%E5%BF%B5-%E5%92%8C%E5%B9%B3%E5%8F%A3%E5%8F%B7%E8%83%8C%E5%90%8E%E7%9A%84%E7%B4%A7%E5%BC%A0%E5%85%B3%E7%B3%BB",
      "source": "rfi.fr",
      "published": 1756913374
    },
    {
      "id": "8e71528ba7cf",
      "title": "普京邀泽连斯基赴莫斯科谈判：“特别军事行动”战士望实现俄方所有目标",
      "url": "https://www.rfi.fr/cn/%E5%9B%BD%E9%99%85/20250903-%E6%99%AE%E4%BA%AC%E9%82%80%E6%B3%BD%E8%BF%9E%E6%96%AF%E5%9F%BA%E8%B5%B4%E8%8E%AB%E6%96%AF%E7%A7%91%E8%B0%88%E5%88%A4-%E7%89%B9%E5%88%AB%E5%86%9B%E4%BA%8B%E8%A1%8C%E5%8A%A8-%E6%88%98%E5%A3%AB%E6%9C%9B%E5%AE%9E%E7%8E%B0%E4%BF%84%E6%89%80%E6%9C%89%E7%9B%AE%E6%A0%87",
      "source": "rfi.fr",
      "published": 1756912244
    },
    {
      "id": "1e046bb1cfc7",
      "title": "德语媒体：俄中关系达到了“前所未有的高度”",
      "url": "https://www.dw.com/zh/德语媒体：俄中关系达到了-前所未有的高度/a-73869626?maca=chi-rss-chi-all-1127-rdf",
      "source": "dw.com",
      "published": 1756910820
    },
    {
      "id": "f4d2493fa1c4",
      "title": "大罢免后赖清德总统改组内阁 但这真的代表危机消失吗？",
      "url": "https://www.rfi.fr/cn/%E4%B8%93%E6%A0%8F%E6%A3%80%E7%B4%A2/%E8%81%9A%E7%84%A6%E5%8F%B0%E6%B5%B7/20250903-%E5%A4%A7%E7%BD%A2%E5%85%8D%E5%90%8E%E8%B5%96%E6%B8%85%E5%BE%B7%E6%80%BB%E7%BB%9F%E6%94%B9%E7%BB%84%E5%86%85%E9%98%81-%E4%BD%86%E8%BF%99%E7%9C%9F%E7%9A%84%E4%BB%A3%E8%A1%A8%E5%8D%B1%E6%9C%BA%E6%B6%88%E5%A4%B1%E5%90%97",
      "source": "rfi.fr",
      "published": 1756910759
    },
    {
      "id": "dbe816770b73",
      "title": "波兰外长：上合组织峰会传出的照片给“反向基辛格”离间俄中的想法泼了冷水",
      "url": "https://www.rfi.fr/cn/%E5%9B%BD%E9%99%85/20250903-%E6%B3%A2%E5%85%B0%E5%A4%96%E9%95%BF-%E4%B8%8A%E5%90%88%E7%BB%84%E7%BB%87%E5%B3%B0%E4%BC%9A%E4%BC%A0%E5%87%BA%E7%9A%84%E7%85%A7%E7%89%87%E7%BB%99-%E5%8F%8D%E5%90%91%E5%9F%BA%E8%BE%9B%E6%A0%BC-%E7%A6%BB%E9%97%B4%E4%BF%84%E4%B8%AD%E7%9A%84%E6%83%B3%E6%B3%95%E6%B3%BC%E4%BA%86%E5%86%B7%E6%B0%B4",
      "source": "rfi.fr",
      "published": 1756910556
    },
    {
      "id": "fbdcb56879b5",
      "title": "出席律師節大會 蕭美琴：法律人以專業讓世界看見台灣",
      "url": "https://udn.com/news/story/6656/8982075",
      "source": "udn.com",
      "published": 1756909418
    },
    {
      "id": "65330ccfd07e",
      "title": "选项党政客克拉出庭：对中国助手间谍活动一无所知",
      "url": "https://www.dw.com/zh/选项党政客克拉出庭：对中国助手间谍活动一无所知/a-73869522?maca=chi-rss-chi-all-1127-rdf",
      "source": "dw.com",
      "published": 1756909320
    },
    {
      "id": "3fedcf40c046",
      "title": "专访：中国新式武器对美、日、台军事部署是巨大挑战",
      "url": "https://www.dw.com/zh/专访：中国新式武器对美、日、台军事部署是巨大挑战/a-73869008?maca=chi-rss-chi-all-1127-rdf",
      "source": "dw.com",
      "published": 1756908960
    },
    {
      "id": "c17568b5a3ea",
      "title": "卡拉斯谈中俄朝伊领导人同台：一个专制联盟正寻求快速建立新的世界秩序",
      "url": "https://www.rfi.fr/cn/%E5%9B%BD%E9%99%85/20250903-%E5%8D%A1%E6%8B%89%E6%96%AF%E8%B0%88%E4%B8%AD%E4%BF%84%E6%9C%9D%E4%BC%8A%E9%A2%86%E5%AF%BC%E4%BA%BA%E5%90%8C%E5%8F%B0-%E4%B8%80%E4%B8%AA%E4%B8%93%E5%88%B6%E8%81%94%E7%9B%9F%E6%AD%A3%E5%AF%BB%E6%B1%82%E5%BF%AB%E9%80%9F%E5%BB%BA%E7%AB%8B%E6%96%B0%E7%9A%84%E4%B8%96%E7%95%8C%E7%A7%A9%E5%BA%8F",
      "source": "rfi.fr",
      "published": 1756907201
    },
    {
      "id": "7b3279fd88ca",
      "title": "德国总理梅尔茨：普京或许是我们这个时代最严重的战争罪犯",
      "url": "https://www.dw.com/zh/德国总理梅尔茨：普京或许是我们这个时代最严重的战争罪犯/a-73868660?maca=chi-rss-chi-all-1127-rdf",
      "source": "dw.com",
      "published": 1756906620
    },
    {
      "id": "e2be06478e8a",
      "title": "陸軍援引四行倉庫史實 強調中華民國才是抗戰主角",
      "url": "https://udn.com/news/story/10930/8981996",
      "source": "udn.com",
      "published": 1756906251
    },
    {
      "id": "ed23b8b73973",
      "title": "國慶主視覺引熱議 韓國瑜親曝背後巧思：向歷史致敬的設計",
      "url": "https://udn.com/news/story/6656/8982006",
      "source": "udn.com",
      "published": 1756906181
    },
    {
      "id": "e40e3bac2aff",
      "title": "賴總統夜宴綠委 首場聚焦財劃法、民生經濟優先",
      "url": "https://udn.com/news/story/6656/8982001",
      "source": "udn.com",
      "published": 1756905893
    },
    {
      "id": "bd31d0295ed9",
      "title": "社福經費大砍逾300億？衛福部急澄清 專家：編列方式改變釀大小眼疑慮",
      "url": "https://udn.com/news/story/124582/8981993",
      "source": "udn.com",
      "published": 1756905605
    },
    {
      "id": "d62e07e89193",
      "title": "视频 爱泼斯坦性犯罪案：3万3千页与罪犯相关文件被公开",
      "url": "https://www.rfi.fr/cn/%E6%94%BF%E6%B2%BB/20250903-%E8%A7%86%E9%A2%91-%E7%88%B1%E6%B3%BC%E6%96%AF%E5%9D%A6%E6%80%A7%E7%8A%AF%E7%BD%AA%E6%A1%88-3%E4%B8%873%E5%8D%83%E9%A1%B5%E4%B8%8E%E7%BD%AA%E7%8A%AF%E7%9B%B8%E5%85%B3%E6%96%87%E4%BB%B6%E8%A2%AB%E5%85%AC%E5%BC%80",
      "source": "rfi.fr",
      "published": 1756904791
    },
    {
      "id": "139c8119727d",
      "title": "會晤賴總統 聖露西亞副總理：支持台灣國家獨立願景",
      "url": "https://udn.com/news/story/6656/8981964",
      "source": "udn.com",
      "published": 1756904659
    },
    {
      "id": "20340b6ff32e",
      "title": "93閱兵觀察：從新武器看中國軍事力量的五大訊號",
      "url": "https://www.bbc.com/zhongwen/articles/c5yvppvj1ljo/trad?at_medium=RSS&at_campaign=rss",
      "source": "bbc.com",
      "published": 1756899615
    },
    {
      "id": "2f7297d27bab",
      "title": "朱立伦：抗战是由国民党领导 中共不断想窜改、扭曲历史",
      "url": "https://www.rfi.fr/cn/%E6%94%BF%E6%B2%BB/20250903-%E6%9C%B1%E7%AB%8B%E4%BC%A6-%E6%8A%97%E6%88%98%E6%98%AF%E7%94%B1%E5%9B%BD%E6%B0%91%E5%85%9A%E9%A2%86%E5%AF%BC-%E4%B8%AD%E5%85%B1%E4%B8%8D%E6%96%AD%E6%83%B3%E7%AA%9C%E6%94%B9%E6%89%AD%E6%9B%B2%E5%8E%86%E5%8F%B2",
      "source": "rfi.fr",
      "published": 1756899212
    },
    {
      "id": "8a5bc9a5d514",
      "title": "【视频】九三阅兵：习普金同框、特朗普发帖、北京市民的自豪",
      "url": "https://www.rfi.fr/cn/%E4%B8%AD%E5%9B%BD/20250903-%E8%A7%86%E9%A2%91-%E4%B9%9D%E4%B8%89%E9%98%85%E5%85%B5-%E4%B9%A0%E6%99%AE%E9%87%91%E5%90%8C%E6%A1%86-%E7%89%B9%E6%9C%97%E6%99%AE%E5%8F%91%E5%B8%96-%E5%8C%97%E4%BA%AC%E5%B8%82%E6%B0%91%E7%9A%84%E8%87%AA%E8%B1%AA",
      "source": "rfi.fr",
      "published": 1756899119
    },
    {
      "id": "44aaea0a51b9",
      "title": "中國「93閱兵」 習近平、金正恩、普京歷史性同框",
      "url": "https://www.bbc.com/zhongwen/articles/c62n33qelg9o/trad?at_medium=RSS&at_campaign=rss",
      "source": "bbc.com",
      "published": 1756897644
    },
    {
      "id": "c4e002ad7bcd",
      "title": "视频 台湾人关注习近平、普京和金正恩同框出席北京阅兵",
      "url": "https://www.rfi.fr/cn/%E4%B8%AD%E5%9B%BD/20250903-%E8%A7%86%E9%A2%91-%E5%8F%B0%E6%B9%BE%E4%BA%BA%E5%85%B3%E6%B3%A8%E4%B9%A0%E8%BF%91%E5%B9%B3-%E6%99%AE%E4%BA%AC%E5%92%8C%E9%87%91%E6%AD%A3%E6%81%A9%E5%90%8C%E6%A1%86%E5%87%BA%E5%B8%AD%E5%8C%97%E4%BA%AC%E9%98%85%E5%85%B5",
      "source": "rfi.fr",
      "published": 1756897453
    },
    {
      "id": "6eb5f78130d2",
      "title": "BBC記者分析中國閱兵：「給予特朗普的明確訊息」",
      "url": "https://www.bbc.com/zhongwen/articles/c4gwqqxlkgjo/trad?at_medium=RSS&at_campaign=rss",
      "source": "bbc.com",
      "published": 1756897329
    },
    {
      "id": "c27cb5e995b3",
      "title": "金正恩“宝贵女儿”北京行引发继承人猜测",
      "url": "https://www.dw.com/zh/金正恩-宝贵女儿-北京行引发继承人猜测/a-73865407?maca=chi-rss-chi-all-1127-rdf",
      "source": "dw.com",
      "published": 1756896060
    },
    {
      "id": "72a0803ad91f",
      "title": "欧盟、南美自贸协议——法国反对 能否批准？",
      "url": "https://www.dw.com/zh/欧盟、南美自贸协议-法国反对-能否批准？/a-73865537?maca=chi-rss-chi-all-1127-rdf",
      "source": "dw.com",
      "published": 1756896000
    },
    {
      "id": "af0cb672ba35",
      "title": "金正恩与普京会谈约两个半小时：会尽一切努力帮助俄罗斯，视为兄弟般责任",
      "url": "https://www.rfi.fr/cn/%E5%9B%BD%E9%99%85/20250903-%E9%87%91%E6%AD%A3%E6%81%A9%E4%B8%8E%E6%99%AE%E4%BA%AC%E4%BC%9A%E8%B0%88%E7%BA%A6%E4%B8%A4%E4%B8%AA%E5%8D%8A%E5%B0%8F%E6%97%B6-%E4%BC%9A%E5%B0%BD%E4%B8%80%E5%88%87%E5%8A%AA%E5%8A%9B%E5%B8%AE%E5%8A%A9%E4%BF%84%E7%BD%97%E6%96%AF%EF%BC%8C%E8%A7%86%E4%B8%BA%E5%85%84%E5%BC%9F%E8%88%AC%E8%B4%A3%E4%BB%BB",
      "source": "rfi.fr",
      "published": 1756895777
    },
    {
      "id": "4d6e9d6156a8",
      "title": "泽连斯基：普京炫耀其不受惩罚，北欧与巴黎峰会寻求明确对乌保障",
      "url": "https://www.rfi.fr/cn/%E5%9B%BD%E9%99%85/20250903-%E6%B3%BD%E8%BF%9E%E6%96%AF%E5%9F%BA-%E6%99%AE%E4%BA%AC%E7%82%AB%E8%80%80%E5%85%B6%E4%B8%8D%E5%8F%97%E6%83%A9%E7%BD%9A%EF%BC%8C%E5%8C%97%E6%AC%A7%E4%B8%8E%E5%B7%B4%E9%BB%8E%E5%B3%B0%E4%BC%9A%E5%AF%BB%E6%B1%82%E6%98%8E%E7%A1%AE%E5%AF%B9%E4%B9%8C%E4%BF%9D%E9%9A%9C",
      "source": "rfi.fr",
      "published": 1756893864
    },
    {
      "id": "debcc133b8a7",
      "title": "韩国会议长禹元植在北京与金正恩碰面并握手致意",
      "url": "https://www.rfi.fr/cn/%E4%BA%9A%E6%B4%B2/20250903-%E9%9F%A9%E5%9B%BD%E4%BC%9A%E8%AE%AE%E9%95%BF%E7%A6%B9%E5%85%83%E6%A4%8D%E5%9C%A8%E5%8C%97%E4%BA%AC%E4%B8%8E%E9%87%91%E6%AD%A3%E6%81%A9%E7%A2%B0%E9%9D%A2%E5%B9%B6%E6%8F%A1%E6%89%8B%E8%87%B4%E6%84%8F",
      "source": "rfi.fr",
      "published": 1756891921
    },
    {
      "id": "3a2e47b402a8",
      "title": "美军称击毙11名自委内瑞拉出海的毒贩，周边国家反应不一",
      "url": "https://www.rfi.fr/cn/%E7%BE%8E%E6%B4%B2/20250903-%E7%BE%8E%E5%86%9B%E7%A7%B0%E5%87%BB%E6%AF%9911%E5%90%8D%E8%87%AA%E5%A7%94%E5%86%85%E7%91%9E%E6%8B%89%E5%87%BA%E6%B5%B7%E7%9A%84%E6%AF%92%E8%B4%A9%EF%BC%8C%E5%91%A8%E8%BE%B9%E5%9B%BD%E5%AE%B6%E5%8F%8D%E5%BA%94%E4%B8%8D%E4%B8%80",
      "source": "rfi.fr",
      "published": 1756890974
    },
    {
      "id": "5835d78ddea8",
      "title": "九三阅兵 温家宝等亮相天安门城楼 胡锦涛、朱镕基未现身",
      "url": "https://www.rfi.fr/cn/%E4%B8%AD%E5%9B%BD/20250903-%E4%B9%9D%E4%B8%89%E9%98%85%E5%85%B5-%E6%B8%A9%E5%AE%B6%E5%AE%9D%E7%AD%89%E4%BA%AE%E7%9B%B8%E5%A4%A9%E5%AE%89%E9%97%A8%E5%9F%8E%E6%A5%BC-%E8%83%A1%E9%94%A6%E6%B6%9B-%E6%9C%B1%E9%95%95%E5%9F%BA%E6%9C%AA%E7%8E%B0%E8%BA%AB",
      "source": "rfi.fr",
      "published": 1756890610
    },
    {
      "id": "fb3fd3763d77",
      "title": "中國民眾如何看待「93閱兵」：中國排面、憶苦思甜、調侃鄰國",
      "url": "https://www.bbc.com/zhongwen/articles/c4gjggrz27xo/trad?at_medium=RSS&at_campaign=rss",
      "source": "bbc.com",
      "published": 1756889828
    },
    {
      "id": "315ad4b5efc4",
      "title": "特朗普促勿忘抗战美国对华巨大流血支持 指中俄朝密谋反美 克宫：没有人在密谋",
      "url": "https://www.rfi.fr/cn/%E5%9B%BD%E9%99%85/20250903-%E7%89%B9%E6%9C%97%E6%99%AE%E4%BF%83%E5%8B%BF%E5%BF%98%E6%8A%97%E6%88%98%E7%BE%8E%E5%9B%BD%E5%AF%B9%E5%8D%8E%E5%B7%A8%E5%A4%A7%E6%B5%81%E8%A1%80%E6%94%AF%E6%8C%81-%E6%8C%87%E4%B8%AD%E4%BF%84%E6%9C%9D%E5%AF%86%E8%B0%8B%E5%8F%8D%E7%BE%8E-%E5%85%8B%E5%AE%AB-%E6%B2%A1%E6%9C%89%E4%BA%BA%E5%9C%A8%E5%AF%86%E8%B0%8B",
      "source": "rfi.fr",
      "published": 1756888594
    },
    {
      "id": "7140c3be8543",
      "title": "央视直播揭习普金谈「长生不老」和「器官移植」话题惹关注",
      "url": "https://www.rfi.fr/cn/%E4%B8%AD%E5%9B%BD/20250903-%E5%A4%AE%E8%A7%86%E7%9B%B4%E6%92%AD%E6%8F%AD%E4%B9%A0%E6%99%AE%E9%87%91%E8%B0%88-%E9%95%BF%E7%94%9F%E4%B8%8D%E8%80%81-%E5%92%8C-%E5%99%A8%E5%AE%98%E7%A7%BB%E6%A4%8D-%E8%AF%9D%E9%A2%98%E6%83%B9%E5%85%B3%E6%B3%A8",
      "source": "rfi.fr",
      "published": 1756887995
    },
    {
      "id": "ae38fe0e1432",
      "title": "中國93閱兵解析：新武器亮相、將領變動及習近平朋友圈三大看點",
      "url": "https://www.bbc.com/zhongwen/articles/c62w2lz6750o/trad?at_medium=RSS&at_campaign=rss",
      "source": "bbc.com",
      "published": 1756887876
    },
    {
      "id": "bbe1b2e6ed53",
      "title": "日本官房长官拒评中国“九三阅兵”  习近平对现代日本只字未提",
      "url": "https://www.rfi.fr/cn/%E4%B8%AD%E5%9B%BD/20250903-%E6%97%A5%E6%9C%AC%E5%AE%98%E6%88%BF%E9%95%BF%E5%AE%98%E6%8B%92%E8%AF%84%E4%B8%AD%E5%9B%BD-%E4%B9%9D%E4%B8%89%E9%98%85%E5%85%B5-%E4%B9%A0%E8%BF%91%E5%B9%B3%E5%AF%B9%E7%8E%B0%E4%BB%A3%E6%97%A5%E6%9C%AC%E5%8F%AA%E5%AD%97%E6%9C%AA%E6%8F%90",
      "source": "rfi.fr",
      "published": 1756887654
    },
    {
      "id": "2192ffba194e",
      "title": "中俄朝领袖同框显示阵营成形 中国借阅兵宣示具构建世界新秩序领导角色",
      "url": "https://www.rfi.fr/cn/%E4%B8%AD%E5%9B%BD/20250903-%E4%B8%AD%E4%BF%84%E6%9C%9D%E9%A2%86%E8%A2%96%E5%90%8C%E6%A1%86%E6%98%BE%E7%A4%BA%E9%98%B5%E8%90%A5%E6%88%90%E5%BD%A2-%E4%B8%AD%E5%9B%BD%E5%80%9F%E9%98%85%E5%85%B5%E5%AE%A3%E7%A4%BA%E5%85%B7%E6%9E%84%E5%BB%BA%E4%B8%96%E7%95%8C%E6%96%B0%E7%A7%A9%E5%BA%8F%E9%A2%86%E5%AF%BC%E8%A7%92%E8%89%B2",
      "source": "rfi.fr",
      "published": 1756885943
    },
    {
      "id": "87cb3109b88b",
      "title": "解码中国：超级大国想超越美国",
      "url": "https://www.dw.com/zh/解码中国：超级大国想超越美国/a-73850216?maca=chi-rss-chi-all-1127-rdf",
      "source": "dw.com",
      "published": 1756880340
    },
    {
      "id": "54864d3a4157",
      "title": "圖輯：2025年中國「9·3 大閱兵」",
      "url": "https://www.bbc.com/zhongwen/articles/c9qyq9rv98jo/trad?at_medium=RSS&at_campaign=rss",
      "source": "bbc.com",
      "published": 1756878528
    },
    {
      "id": "8cea5e19538e",
      "title": "金正恩携女儿金主爱访华，向世界传递接班人信号",
      "url": "https://cn.nytimes.com/asia-pacific/20250903/kim-jong-un-ju-ae-china/?utm_source=RSS",
      "source": "cn.nytimes.com",
      "published": 1756873349
    },
    {
      "id": "19c551961b0d",
      "title": "中俄朝領袖同框九三閱兵 川普批「密謀反美」",
      "url": "https://www.dw.com/zh/中俄朝領袖同框九三閱兵-川普批「密謀反美」/a-73859875?maca=chi-rss-chi-all-1127-rdf",
      "source": "dw.com",
      "published": 1756873080
    },
    {
      "id": "f7b37320cb6e",
      "title": "中國抗戰勝利80週年閱兵 習近平普京金正恩同台亮相",
      "url": "https://www.bbc.com/zhongwen/articles/c2090d33pn1o/trad?at_medium=RSS&at_campaign=rss",
      "source": "bbc.com",
      "published": 1756871841
    },
    {
      "id": "1be572023df9",
      "title": "反壟斷案：Google不須分拆Chrome瀏覽器",
      "url": "https://www.bbc.com/zhongwen/articles/c4gmgr7p8lpo/trad?at_medium=RSS&at_campaign=rss",
      "source": "bbc.com",
      "published": 1756871306
    },
    {
      "id": "a812879a7402",
      "title": "普京稱讚俄中關係「前所未有」",
      "url": "https://www.bbc.com/zhongwen/articles/ce8385lz9zeo/trad?at_medium=RSS&at_campaign=rss",
      "source": "bbc.com",
      "published": 1756865906
    },
    {
      "id": "04bf8b3db6fc",
      "title": "习近平高规格接待普京，中俄团结一致制衡西方",
      "url": "https://cn.nytimes.com/china/20250903/china-putin-xi/?utm_source=RSS",
      "source": "cn.nytimes.com",
      "published": 1756862895
    },
    {
      "id": "eaf3d292dd66",
      "title": "金正恩攜女兒金主愛抵達北京出席中國閱兵式",
      "url": "https://www.bbc.com/zhongwen/articles/cnv7v9lr2l2o/trad?at_medium=RSS&at_campaign=rss",
      "source": "bbc.com",
      "published": 1756859268
    },
    {
      "id": "8c57aa858e9d",
      "title": "法国华人巴黎凯旋门下献花，纪念抗日战争胜利80周年",
      "url": "https://www.rfi.fr/cn/%E6%B3%95%E5%9B%BD/20250902-%E6%B3%95%E5%9B%BD%E5%8D%8E%E4%BA%BA%E5%B7%B4%E9%BB%8E%E5%87%AF%E6%97%8B%E9%97%A8%E4%B8%8B%E7%8C%AE%E8%8A%B1%EF%BC%8C%E7%BA%AA%E5%BF%B5%E6%8A%97%E6%97%A5%E6%88%98%E4%BA%89%E8%83%9C%E5%88%A980%E5%91%A8%E5%B9%B4",
      "source": "rfi.fr",
      "published": 1756856813
    },
    {
      "id": "23db642592bc",
      "title": "“九三”阅兵看点：中国军事实力和威权领袖“朋友圈”",
      "url": "https://cn.nytimes.com/china/20250902/china-parade-putin-kim/?utm_source=RSS",
      "source": "cn.nytimes.com",
      "published": 1756856578
    },
    {
      "id": "f6ab81ccbadf",
      "title": "习近平与普京：战略搭档、复杂的联盟",
      "url": "https://www.rfi.fr/cn/%E4%B8%93%E6%A0%8F%E6%A3%80%E7%B4%A2/%E6%B3%95%E5%9B%BD%E4%B8%96%E7%95%8C%E6%8A%A5/20250902-%E4%B9%A0%E8%BF%91%E5%B9%B3%E4%B8%8E%E6%99%AE%E4%BA%AC-%E6%88%98%E7%95%A5%E6%90%AD%E6%A1%A3-%E5%A4%8D%E6%9D%82%E7%9A%84%E8%81%94%E7%9B%9F",
      "source": "rfi.fr",
      "published": 1756856539
    },
    {
      "id": "7665c8002fc2",
      "title": "特朗普稱不認為中國正組「國際反美聯盟」：「它更需要我們」",
      "url": "https://www.bbc.com/zhongwen/articles/c5y3yz34ewvo/trad?at_medium=RSS&at_campaign=rss",
      "source": "bbc.com",
      "published": 1756856120
    },
    {
      "id": "dcc1a8656e87",
      "title": "郑旭光：九三阅兵，习普金三人同台呈现出新冷战秩序",
      "url": "https://www.rfi.fr/cn/%E4%B8%93%E6%A0%8F%E6%A3%80%E7%B4%A2/%E5%9B%BD%E9%99%85%E7%BA%B5%E6%A8%AA/20250902-%E4%B8%93%E8%AE%BF-%E4%B9%A0%E6%99%AE%E9%87%91%E4%B8%89%E4%BA%BA%E5%90%8C%E5%8F%B0%E5%91%88%E7%8E%B0%E5%87%BA%E6%96%B0%E5%86%B7%E6%88%98%E7%A7%A9%E5%BA%8F",
      "source": "rfi.fr",
      "published": 1756853968
    },
    {
      "id": "04440e0441af",
      "title": "习近平主持阅兵式：煽动民族主义，展示中国影响力",
      "url": "https://cn.nytimes.com/china/20250903/xi-putin-kim-parade/?utm_source=RSS",
      "source": "cn.nytimes.com",
      "published": 1756851238
    },
    {
      "id": "9cf1aa7028f0",
      "title": "特朗普：我对普京总统非常失望",
      "url": "https://www.rfi.fr/cn/%E7%BE%8E%E6%B4%B2/20250902-%E7%89%B9%E6%9C%97%E6%99%AE-%E6%88%91%E5%AF%B9%E6%99%AE%E4%BA%AC%E6%80%BB%E7%BB%9F%E9%9D%9E%E5%B8%B8%E5%A4%B1%E6%9C%9B",
      "source": "rfi.fr",
      "published": 1756847948
    },
    {
      "id": "27bd5e846708",
      "title": "乌克兰绝不同意将俄罗斯对札波罗热核电厂占领行为合法化",
      "url": "https://www.rfi.fr/cn/%E6%AC%A7%E6%B4%B2/20250902-%E4%B9%8C%E5%85%8B%E5%85%B0%E7%BB%9D%E4%B8%8D%E5%90%8C%E6%84%8F%E5%B0%86%E4%BF%84%E7%BD%97%E6%96%AF%E5%AF%B9%E6%9C%AD%E6%B3%A2%E7%BD%97%E7%83%AD%E6%A0%B8%E7%94%B5%E5%8E%82%E5%8D%A0%E9%A2%86%E8%A1%8C%E4%B8%BA%E5%90%88%E6%B3%95%E5%8C%96",
      "source": "rfi.fr",
      "published": 1756847857
    },
    {
      "id": "d47cc16cbb8d",
      "title": "马赛发生持刀袭击事件：5人受伤      袭击者已被击毙",
      "url": "https://www.rfi.fr/cn/%E6%B3%95%E5%9B%BD/20250902-%E9%A9%AC%E8%B5%9B%E5%8F%91%E7%94%9F%E6%8C%81%E5%88%80%E8%A2%AD%E5%87%BB%E4%BA%8B%E4%BB%B6-5%E4%BA%BA%E5%8F%97%E4%BC%A4-%E8%A2%AD%E5%87%BB%E8%80%85%E5%B7%B2%E8%A2%AB%E5%87%BB%E6%AF%99",
      "source": "rfi.fr",
      "published": 1756847780
    },
    {
      "id": "e3048c2b4706",
      "title": "援华抗战美国飞虎队后代被邀观看北京阅兵仪式",
      "url": "https://www.rfi.fr/cn/%E4%B8%AD%E5%9B%BD/20250902-%E6%8F%B4%E5%8D%8E%E6%8A%97%E6%88%98%E7%BE%8E%E5%9B%BD%E9%A3%9E%E8%99%8E%E9%98%9F%E5%90%8E%E4%BB%A3%E8%A2%AB%E9%82%80%E8%A7%82%E7%9C%8B%E5%8C%97%E4%BA%AC%E9%98%85%E5%85%B5%E4%BB%AA%E5%BC%8F",
      "source": "rfi.fr",
      "published": 1756847499
    },
    {
      "id": "4ae025e3e756",
      "title": "重庆反共标语事件：一场监控“天网”下的抗议与行为艺术",
      "url": "https://cn.nytimes.com/china/20250903/china-chongqing-protest/?utm_source=RSS",
      "source": "cn.nytimes.com",
      "published": 1756846504
    },
    {
      "id": "7aa0abdb2fa5",
      "title": "美法官判特朗普出兵洛杉矶违法　恐影响其他城市部署计划",
      "url": "https://www.rfi.fr/cn/%E6%94%BF%E6%B2%BB/20250902-%E7%BE%8E%E6%B3%95%E5%AE%98%E5%88%A4%E7%89%B9%E6%9C%97%E6%99%AE%E5%87%BA%E5%85%B5%E6%B4%9B%E6%9D%89%E7%9F%B6%E8%BF%9D%E6%B3%95-%E6%81%90%E5%BD%B1%E5%93%8D%E5%85%B6%E4%BB%96%E5%9F%8E%E5%B8%82%E9%83%A8%E7%BD%B2%E8%AE%A1%E5%88%92",
      "source": "rfi.fr",
      "published": 1756844846
    },
    {
      "id": "4fea2b40eeee",
      "title": "参加北京阅兵：瑞士前总统和斯洛伐克总理令人侧目",
      "url": "https://www.rfi.fr/cn/%E4%B8%93%E6%A0%8F%E6%A3%80%E7%B4%A2/%E8%A6%81%E9%97%BB%E5%88%86%E6%9E%90/20250902-%E5%8F%82%E5%8A%A0%E5%8C%97%E4%BA%AC%E9%98%85%E5%85%B5-%E7%91%9E%E5%A3%AB%E5%89%8D%E6%80%BB%E7%BB%9F%E5%92%8C%E6%96%AF%E6%B4%9B%E4%BC%90%E5%85%8B%E6%80%BB%E7%90%86%E4%BB%A4%E4%BA%BA%E4%BE%A7%E7%9B%AE",
      "source": "rfi.fr",
      "published": 1756843084
    },
    {
      "id": "5938037edc42",
      "title": "中国“九三”阅兵现场",
      "url": "https://cn.nytimes.com/china/20250903/china-military-parade/?utm_source=RSS",
      "source": "cn.nytimes.com",
      "published": 1756841255
    },
    {
      "id": "803be8545458",
      "title": "揭秘金正恩专列“太阳号”：金氏家族的豪华防弹慢车",
      "url": "https://cn.nytimes.com/asia-pacific/20250903/kim-north-korea-train/?utm_source=RSS",
      "source": "cn.nytimes.com",
      "published": 1756834262
    },
    {
      "id": "58cc230d734a",
      "title": "每周时事分析：中国阅兵下的东北亚局势及影响",
      "url": "https://www.ftchinese.com/story/001107500",
      "source": "ftchinese.com",
      "published": 1756828800
    },
    {
      "id": "966b9d792162",
      "title": "中国举行里程碑式的阅兵",
      "url": "https://www.ftchinese.com/story/001107506",
      "source": "ftchinese.com",
      "published": 1756828800
    },
    {
      "id": "9eca8dd21968",
      "title": "香港甲级写字楼租赁市场升温",
      "url": "https://www.ftchinese.com/story/001107503",
      "source": "ftchinese.com",
      "published": 1756828800
    },
    {
      "id": "c6b8ca6f679f",
      "title": "美国限制台积电对华出口芯片制造设备",
      "url": "https://www.ftchinese.com/story/001107502",
      "source": "ftchinese.com",
      "published": 1756828800
    },
    {
      "id": "a51f56eba5cf",
      "title": "英国财政状况有那么糟糕吗？",
      "url": "https://www.ftchinese.com/story/001107501",
      "source": "ftchinese.com",
      "published": 1756828800
    },
    {
      "id": "6be6086feb9d",
      "title": "美国股市周二下跌，科技股延续震荡走势",
      "url": "https://www.ftchinese.com/story/001107499",
      "source": "ftchinese.com",
      "published": 1756828800
    },
    {
      "id": "3ea2abbca766",
      "title": "奇异滞涨、劳动力“双缩“与美联储降息",
      "url": "https://www.ftchinese.com/story/001107467",
      "source": "ftchinese.com",
      "published": 1756828800
    },
    {
      "id": "d928d12a5e5b",
      "title": "特朗普入股英特尔：美国重振芯片产业的前奏？",
      "url": "https://www.ftchinese.com/story/001107492",
      "source": "ftchinese.com",
      "published": 1756828800
    },
    {
      "id": "aebc8394920e",
      "title": "最强果链企业上市，立讯精密从零到3,000亿王国",
      "url": "https://www.ftchinese.com/story/001107495",
      "source": "ftchinese.com",
      "published": 1756828800
    },
    {
      "id": "f61016d1a4eb",
      "title": "业绩劲升股价反跌，蜜雪冰城缘何遭冷遇？",
      "url": "https://www.ftchinese.com/story/001107496",
      "source": "ftchinese.com",
      "published": 1756828800
    },
    {
      "id": "a8e222395068",
      "title": "历史追忆：“特普会”的今与昔",
      "url": "https://www.ftchinese.com/story/001107497",
      "source": "ftchinese.com",
      "published": 1756828800
    },
    {
      "id": "ba74740b29a2",
      "title": "反对党获不利裁决后土耳其股市下滑",
      "url": "https://www.ftchinese.com/story/001107498",
      "source": "ftchinese.com",
      "published": 1756828800
    },
    {
      "id": "3a47d9905511",
      "title": "再次为选择党助选  马斯克称德国“末日”将至",
      "url": "https://www.dw.com/zh/再次为选择党助选-马斯克称德国-末日-将至/a-73854284?maca=chi-rss-chi-all-1127-rdf",
      "source": "dw.com",
      "published": 1756824840
    },
    {
      "id": "572fe6a0c37d",
      "title": "普京：俄罗斯不反对乌克兰加入欧盟",
      "url": "https://www.dw.com/zh/普京：俄罗斯不反对乌克兰加入欧盟/a-73854079?maca=chi-rss-chi-all-1127-rdf",
      "source": "dw.com",
      "published": 1756822320
    },
    {
      "id": "4318d3dbe5f2",
      "title": "從毛澤東到習近平，一文看清1949年以來17次天安門閱兵的異同",
      "url": "https://www.bbc.com/zhongwen/articles/cde3erl8lpdo/trad?at_medium=RSS&at_campaign=rss",
      "source": "bbc.com",
      "published": 1756821839
    },
    {
      "id": "800fba5825cb",
      "title": "德语媒体：中国正在重塑国际秩序",
      "url": "https://www.dw.com/zh/德语媒体：中国正在重塑国际秩序/a-73852859?maca=chi-rss-chi-all-1127-rdf",
      "source": "dw.com",
      "published": 1756821120
    },
    {
      "id": "b8445e3c5525",
      "title": "上合峰會緊連九三閱兵：中國為首的反美聯盟走進新時代？",
      "url": "https://www.bbc.com/zhongwen/articles/cgm2mxgxlgro/trad?at_medium=RSS&at_campaign=rss",
      "source": "bbc.com",
      "published": 1756820445
    },
    {
      "id": "c4f90fa0c1df",
      "title": "中俄20多项合作签约 西伯利亚二号线有望落实",
      "url": "https://www.dw.com/zh/中俄20多项合作签约-西伯利亚二号线有望落实/a-73849590?maca=chi-rss-chi-all-1127-rdf",
      "source": "dw.com",
      "published": 1756811580
    },
    {
      "id": "a116afb8b29d",
      "title": "記憶的煙硝：80年後兩岸歷史教育如何談二戰？",
      "url": "https://www.dw.com/zh/記憶的煙硝：80年後兩岸歷史教育如何談二戰？/a-73847317?maca=chi-rss-chi-all-1127-rdf",
      "source": "dw.com",
      "published": 1756805460
    },
    {
      "id": "99f2783308bd",
      "title": "習近平在世界舞台的重大時刻前夕，北京收緊市內管制",
      "url": "https://www.bbc.com/zhongwen/articles/c05e56qd2e2o/trad?at_medium=RSS&at_campaign=rss",
      "source": "bbc.com",
      "published": 1756801622
    },
    {
      "id": "0784a2e313d8",
      "title": "送貨司機之死如何引發印尼騷亂",
      "url": "https://www.bbc.com/zhongwen/articles/c1dxdn1313no/trad?at_medium=RSS&at_campaign=rss",
      "source": "bbc.com",
      "published": 1756800396
    },
    {
      "id": "1afdeb7dd611",
      "title": "儘管遭盟友反對  特朗普仍為「提供60萬中國學生簽證」辯護",
      "url": "https://www.bbc.com/zhongwen/articles/c4glgk05z2vo/trad?at_medium=RSS&at_campaign=rss",
      "source": "bbc.com",
      "published": 1756797487
    },
    {
      "id": "eb378f4adf5c",
      "title": "武漢大學「性騷擾」案餘波：如何在維權和「誣告」之間尋求解決之道",
      "url": "https://www.bbc.com/zhongwen/articles/cx29qe530wro/trad?at_medium=RSS&at_campaign=rss",
      "source": "bbc.com",
      "published": 1756794830
    },
    {
      "id": "29bdb126c67a",
      "title": "《天津宣言》未提烏克蘭 習近平幫普丁留面子？",
      "url": "https://www.dw.com/zh/《天津宣言》未提烏克蘭-習近平幫普丁留面子？/a-73843836?maca=chi-rss-chi-all-1127-rdf",
      "source": "dw.com",
      "published": 1756788660
    },
    {
      "id": "94f995317e61",
      "title": "中国政府为何要为电动汽车热潮“降温”",
      "url": "https://cn.nytimes.com/business/20250902/china-electric-vehicles-overcapacity/?utm_source=RSS",
      "source": "cn.nytimes.com",
      "published": 1756787486
    },
    {
      "id": "9ae7c583ca22",
      "title": "金正恩已乘火車進入中國  朝鮮領導人70年來首次參加中國閱兵",
      "url": "https://www.bbc.com/zhongwen/articles/cq8780nl0weo/trad?at_medium=RSS&at_campaign=rss",
      "source": "bbc.com",
      "published": 1756787022
    },
    {
      "id": "28fad6982200",
      "title": "莫迪為何進津卻不入京，中印互動背後的「特朗普因素」等觀察重點",
      "url": "https://www.bbc.com/zhongwen/articles/c6202xw5y31o/trad?at_medium=RSS&at_campaign=rss",
      "source": "bbc.com",
      "published": 1756783081
    },
    {
      "id": "b1dad6e00159",
      "title": "微笑、牵手、亲密交谈：中印俄领导人展示团结",
      "url": "https://cn.nytimes.com/china/20250902/china-xi-putin-modi/?utm_source=RSS",
      "source": "cn.nytimes.com",
      "published": 1756779583
    },
    {
      "id": "a429d343ebb2",
      "title": "保護國家安全還是排外？美國德州限制華人擁有或租賃房產",
      "url": "https://www.bbc.com/zhongwen/articles/c3dp7gle4y2o/trad?at_medium=RSS&at_campaign=rss",
      "source": "bbc.com",
      "published": 1756773004
    },
    {
      "id": "8787b9ff51db",
      "title": "極端高溫如何「融化」你的DNA並加速衰老？",
      "url": "https://www.bbc.com/zhongwen/articles/cjeyqjp50kxo/trad?at_medium=RSS&at_campaign=rss",
      "source": "bbc.com",
      "published": 1756772926
    },
    {
      "id": "38402e3c8911",
      "title": "特朗普与莫迪为何“翻脸”：诺贝尔奖和一通电话",
      "url": "https://cn.nytimes.com/usa/20250903/trump-modi-india/?utm_source=RSS",
      "source": "cn.nytimes.com",
      "published": 1756759944
    },
    {
      "id": "c2538a5f27e7",
      "title": "国产机器人助推中国提升出口份额",
      "url": "https://www.ftchinese.com/story/001107493",
      "source": "ftchinese.com",
      "published": 1756742400
    },
    {
      "id": "50af00df409c",
      "title": "中俄签署重大天然气管道协议",
      "url": "https://www.ftchinese.com/story/001107491",
      "source": "ftchinese.com",
      "published": 1756742400
    },
    {
      "id": "d44b824d94fa",
      "title": "美国ETF数量超过个股——别大惊小怪",
      "url": "https://www.ftchinese.com/story/001107490",
      "source": "ftchinese.com",
      "published": 1756742400
    },
    {
      "id": "666706f2661c",
      "title": "发展中国家置换美元债务以降低借贷成本",
      "url": "https://www.ftchinese.com/story/001107489",
      "source": "ftchinese.com",
      "published": 1756742400
    },
    {
      "id": "737fdef88ec1",
      "title": "人民币对美元汇率升至特朗普胜选以来最高水平",
      "url": "https://www.ftchinese.com/story/001107488",
      "source": "ftchinese.com",
      "published": 1756742400
    },
    {
      "id": "87ff877cb642",
      "title": "阶层：剧变时代的新坐标",
      "url": "https://www.ftchinese.com/story/001107477",
      "source": "ftchinese.com",
      "published": 1756742400
    },
    {
      "id": "685999f39c43",
      "title": "Lex专栏：救救秘书这个职业",
      "url": "https://www.ftchinese.com/story/001107487",
      "source": "ftchinese.com",
      "published": 1756742400
    },
    {
      "id": "b839e2f54926",
      "title": "小班化教学应快速提上议事日程",
      "url": "https://www.ftchinese.com/story/001107485",
      "source": "ftchinese.com",
      "published": 1756742400
    },
    {
      "id": "130e58c17ae8",
      "title": "客座评论：金正恩出席九三阅兵 北京与平壤的双重算计",
      "url": "https://www.dw.com/zh/客座评论：金正恩出席九三阅兵-北京与平壤的双重算计/a-73832506?maca=chi-rss-chi-all-1127-rdf",
      "source": "dw.com",
      "published": 1756734360
    },
    {
      "id": "9d1cb7ae7177",
      "title": "德语媒体：对北京来说，西方已变得无足轻重",
      "url": "https://www.dw.com/zh/德语媒体：对北京来说，西方已变得无足轻重/a-73837015?maca=chi-rss-chi-all-1127-rdf",
      "source": "dw.com",
      "published": 1756733940
    },
    {
      "id": "9c9230d4bcbd",
      "title": "军事秀肌肉：九·三阅兵将展示哪些武器？",
      "url": "https://www.dw.com/zh/军事秀肌肉：九·三阅兵将展示哪些武器？/a-73833193?maca=chi-rss-chi-all-1127-rdf",
      "source": "dw.com",
      "published": 1756724820
    },
    {
      "id": "c5f4c5479d53",
      "title": "中國海軍以驚人速度擴張，正在追上美國",
      "url": "https://www.bbc.com/zhongwen/articles/c4gqnz1ezl4o/trad?at_medium=RSS&at_campaign=rss",
      "source": "bbc.com",
      "published": 1756719392
    },
    {
      "id": "63e6eda577cb",
      "title": "普京莫迪抵達中國參加上合峰會，但美中印貿易戰使峰會蒙上陰影",
      "url": "https://www.bbc.com/zhongwen/articles/clyv43nzgypo/trad?at_medium=RSS&at_campaign=rss",
      "source": "bbc.com",
      "published": 1756706106
    },
    {
      "id": "ad19b31f9b25",
      "title": "中国购物中心建设热潮背后的繁荣与困境",
      "url": "https://cn.nytimes.com/business/20250901/china-shopping-malls/?utm_source=RSS",
      "source": "cn.nytimes.com",
      "published": 1756702038
    },
    {
      "id": "7218cc7d8393",
      "title": "习近平利用峰会、阅兵和历史展示中国影响力",
      "url": "https://cn.nytimes.com/china/20250901/xi-putin-modi-china-summit/?utm_source=RSS",
      "source": "cn.nytimes.com",
      "published": 1756691196
    },
    {
      "id": "80147fafdd1d",
      "title": "五年後回看  新冠疫情期間的封鎖對孩子產生什麼長遠影響？",
      "url": "https://www.bbc.com/zhongwen/articles/cvgv7xn0pqyo/trad?at_medium=RSS&at_campaign=rss",
      "source": "bbc.com",
      "published": 1756686172
    },
    {
      "id": "d1f6601b5fb7",
      "title": "印度曾是“中国制造”的替代方案，特朗普改变了一切",
      "url": "https://cn.nytimes.com/business/20250901/india-china-trump-tariffs/?utm_source=RSS",
      "source": "cn.nytimes.com",
      "published": 1756670708
    },
    {
      "id": "2f9ceeda116b",
      "title": "中国移民在伦敦认罪：三年间至少犯下24项性犯罪",
      "url": "https://cn.nytimes.com/world/20250901/london-sexual-assaults/?utm_source=RSS",
      "source": "cn.nytimes.com",
      "published": 1756667678
    },
    {
      "id": "3c6c97b4d4b3",
      "title": "《南京照相馆》等抗战电影热映，记录历史还是灌输仇恨？",
      "url": "https://cn.nytimes.com/china/20250901/china-japan-wwii-nationalism/?utm_source=RSS",
      "source": "cn.nytimes.com",
      "published": 1756661933
    },
    {
      "id": "2b285cfa7031",
      "title": "墙外文摘：金砖国家反击特朗普，中国并非替代目标",
      "url": "https://www.dw.com/zh/墙外文摘：金砖国家反击特朗普，中国并非替代目标/a-73826493?maca=chi-rss-chi-all-1127-rdf",
      "source": "dw.com",
      "published": 1756649340
    },
    {
      "id": "47a59d4c4716",
      "title": "需求仍疲软 中国制造业连续五个月在收缩区间",
      "url": "https://www.dw.com/zh/需求仍疲软-中国制造业连续五个月在收缩区间/a-73825925?maca=chi-rss-chi-all-1127-rdf",
      "source": "dw.com",
      "published": 1756640520
    },
    {
      "id": "98130a8634a0",
      "title": "DW事实核查：如何不被AI聊天机器人误导？",
      "url": "https://www.dw.com/zh/dw事实核查：如何不被ai聊天机器人误导？/a-73764367?maca=chi-rss-chi-all-1127-rdf",
      "source": "dw.com",
      "published": 1756624260
    },
    {
      "id": "5cf4b2a35e8a",
      "title": "拉美掀起铁路建设热潮 中国影响力处处可见",
      "url": "https://www.dw.com/zh/拉美掀起铁路建设热潮-中国影响力处处可见/a-73772902?maca=chi-rss-chi-all-1127-rdf",
      "source": "dw.com",
      "published": 1756624200
    },
    {
      "id": "ffc0c38a3249",
      "title": "DW事实核查：如何识别“冒牌”新闻？",
      "url": "https://www.dw.com/zh/dw事实核查：如何识别-冒牌-新闻？/a-73779754?maca=chi-rss-chi-all-1127-rdf",
      "source": "dw.com",
      "published": 1756624140
    },
    {
      "id": "298f45d39b19",
      "title": "纳粹劫掠艺术品“现身”房产广告 警方扑了个空",
      "url": "https://www.dw.com/zh/纳粹劫掠艺术品-现身-房产广告-警方扑了个空/a-73810547?maca=chi-rss-chi-news-3224-rdf",
      "source": "dw.com",
      "published": 1756624080
    },
    {
      "id": "28599e0c4b52",
      "title": "纳粹劫掠艺术品“现身”房产广告 警方扑了个空",
      "url": "https://www.dw.com/zh/纳粹劫掠艺术品-现身-房产广告-警方扑了个空/a-73810547?maca=chi-rss-chi-all-1127-rdf",
      "source": "dw.com",
      "published": 1756624080
    },
    {
      "id": "3b2a839ee5ee",
      "title": "习莫普天津会晤：金砖国家被特朗普越挫越旺？",
      "url": "https://www.dw.com/zh/习莫普天津会晤：金砖国家被特朗普越挫越旺？/a-73819601?maca=chi-rss-chi-all-1127-rdf",
      "source": "dw.com",
      "published": 1756551120
    },
    {
      "id": "9c5d015a18b7",
      "title": "法庭裁决加征关税违宪 特朗普诉诸最高院",
      "url": "https://www.dw.com/zh/法庭裁决加征关税违宪-特朗普诉诸最高院/a-73819143?maca=chi-rss-chi-all-1127-rdf",
      "source": "dw.com",
      "published": 1756546980
    },
    {
      "id": "7ebc75ed3f18",
      "title": "印度和巴基斯坦能否解决印度河水资源争端？",
      "url": "https://www.dw.com/zh/印度和巴基斯坦能否解决印度河水资源争端？/a-73799596?maca=chi-rss-chi-all-1127-rdf",
      "source": "dw.com",
      "published": 1756534860
    },
    {
      "id": "df07766b37fa",
      "title": "「每日最多兩小時」：日本豐明市倡限使用手機時間引發爭議",
      "url": "https://www.bbc.com/zhongwen/articles/c2063mpr4yro/trad?at_medium=RSS&at_campaign=rss",
      "source": "bbc.com",
      "published": 1756515304
    },
    {
      "id": "4d4758e9ed46",
      "title": "欧盟拟对美国商品免税 换取特朗普小幅让步",
      "url": "https://www.dw.com/zh/欧盟拟对美国商品免税-换取特朗普小幅让步/a-73812857?maca=chi-rss-chi-all-1127-rdf",
      "source": "dw.com",
      "published": 1756477980
    },
    {
      "id": "3d0ea6872123",
      "title": "德语媒体：人口危机- 中国会重蹈古罗马覆辙吗？",
      "url": "https://www.dw.com/zh/德语媒体：人口危机-中国会重蹈古罗马覆辙吗？/a-73812631?maca=chi-rss-chi-all-1127-rdf",
      "source": "dw.com",
      "published": 1756476960
    },
    {
      "id": "d26f94624199",
      "title": "俄羅斯導彈擊穿基輔居民樓致23人死亡  歐盟辦公室受損",
      "url": "https://www.bbc.com/zhongwen/articles/c754p6yz94vo/trad?at_medium=RSS&at_campaign=rss",
      "source": "bbc.com",
      "published": 1756458607
    },
    {
      "id": "72b5a0304ef7",
      "title": "「規模最大」的上合天津峰會  兩個最大鄰國是否在向北京靠攏？",
      "url": "https://www.bbc.com/zhongwen/articles/c9qyzgjr3l5o/trad?at_medium=RSS&at_campaign=rss",
      "source": "bbc.com",
      "published": 1756455259
    },
    {
      "id": "2e3476b37fdf",
      "title": "中国社保新规惹争议，强制缴纳引发广泛焦虑",
      "url": "https://cn.nytimes.com/china/20250829/china-social-security/?utm_source=RSS",
      "source": "cn.nytimes.com",
      "published": 1756441017
    },
    {
      "id": "7f37c927d030",
      "title": "美國全面取消小額包裹關稅豁免 衝擊全球電商郵務",
      "url": "https://www.dw.com/zh/美國全面取消小額包裹關稅豁免-衝擊全球電商郵務/a-73802803?maca=chi-rss-chi-all-1127-rdf",
      "source": "dw.com",
      "published": 1756440240
    },
    {
      "id": "063637d03ebd",
      "title": "被拒絕的一代？和領英高管討論人工智能衝擊下年輕人的求職難題",
      "url": "https://www.bbc.com/zhongwen/articles/c36jlkdld0xo/trad?at_medium=RSS&at_campaign=rss",
      "source": "bbc.com",
      "published": 1756433042
    },
    {
      "id": "012cccb5360c",
      "title": "威权领导人“聚会”：金正恩普京将出席北京“九三阅兵”",
      "url": "https://cn.nytimes.com/china/20250829/kim-jong-un-military-parade-beijing/?utm_source=RSS",
      "source": "cn.nytimes.com",
      "published": 1756432283
    },
    {
      "id": "fd0a1fb3c468",
      "title": "总理佩通坦被免职，泰国政局为何一直动荡？",
      "url": "https://cn.nytimes.com/asia-pacific/20250829/thailand-politics-crisis/?utm_source=RSS",
      "source": "cn.nytimes.com",
      "published": 1756418230
    },
    {
      "id": "9fe6b8abaa01",
      "title": "我女儿自杀前和ChatGPT说了什么",
      "url": "https://cn.nytimes.com/opinion/20250828/chat-gpt-mental-health-suicide/?utm_source=RSS",
      "source": "cn.nytimes.com",
      "published": 1756413813
    },
    {
      "id": "33ba6a34580b",
      "title": "久坐危害有多大？比你想的更严重",
      "url": "https://cn.nytimes.com/health/20250829/sitting-down-sedentary-effects-tips/?utm_source=RSS",
      "source": "cn.nytimes.com",
      "published": 1756409117
    },
    {
      "id": "650ef774d044",
      "title": "德语媒体：中国如何将我们变成中国人",
      "url": "https://www.dw.com/zh/德语媒体：中国如何将我们变成中国人/a-73800268?maca=chi-rss-chi-all-1127-rdf",
      "source": "dw.com",
      "published": 1756392480
    },
    {
      "id": "fdf02ea63de9",
      "title": "长平观察：特朗普不懂中国留学生",
      "url": "https://www.dw.com/zh/长平观察：特朗普不懂中国留学生/a-73798933?maca=chi-rss-chi-all-1127-rdf",
      "source": "dw.com",
      "published": 1756387740
    },
    {
      "id": "302db646cc03",
      "title": "时代变了！欧洲国家各显神通征召兵员",
      "url": "https://www.dw.com/zh/时代变了！欧洲国家各显神通征召兵员/a-73798923?maca=chi-rss-chi-all-1127-rdf",
      "source": "dw.com",
      "published": 1756386540
    },
    {
      "id": "aca159d23718",
      "title": "欲降低對美依賴 媒體：中國新建3廠因應華為需求",
      "url": "https://www.dw.com/zh/欲降低對美依賴-媒體：中國新建3廠因應華為需求/a-73790322?maca=chi-rss-chi-all-1127-rdf",
      "source": "dw.com",
      "published": 1756357740
    },
    {
      "id": "df59979dfde2",
      "title": "美國明州天主教小學槍擊案釀20人傷亡",
      "url": "https://www.dw.com/zh/美國明州天主教小學槍擊案釀20人傷亡/a-73790255?maca=chi-rss-chi-news-3224-rdf",
      "source": "dw.com",
      "published": 1756355400
    },
    {
      "id": "b38539b21827",
      "title": "普京金正恩確定參加93閱兵，如何觀察背後的權力展示、智能戰爭、盟友變遷以及兩岸角力",
      "url": "https://www.bbc.com/zhongwen/articles/cwy0j4gl957o/trad?at_medium=RSS&at_campaign=rss",
      "source": "bbc.com",
      "published": 1756349662
    },
    {
      "id": "0cbd206ef520",
      "title": "越南南沙建島低調超車中國  南海造島競賽風雲再起？",
      "url": "https://www.bbc.com/zhongwen/articles/cdj20vkd9m3o/trad?at_medium=RSS&at_campaign=rss",
      "source": "bbc.com",
      "published": 1756340386
    },
    {
      "id": "c8c0525b7aa2",
      "title": "德语媒体：莫迪的两难境地",
      "url": "https://www.dw.com/zh/德语媒体：莫迪的两难境地/a-73785151?maca=chi-rss-chi-all-1127-rdf",
      "source": "dw.com",
      "published": 1756303260
    },
    {
      "id": "e4c0ef2266b0",
      "title": "惩罚购买俄石油：美国对印度50%高关税生效",
      "url": "https://www.dw.com/zh/惩罚购买俄石油：美国对印度50-高关税生效/a-73780597?maca=chi-rss-chi-all-1127-rdf",
      "source": "dw.com",
      "published": 1756292040
    },
    {
      "id": "a0c9610d5117",
      "title": "台灣國防預算創新高，民眾怎麼看？",
      "url": "https://www.bbc.com/zhongwen/articles/cqjyxe4x5g4o/trad?at_medium=RSS&at_campaign=rss",
      "source": "bbc.com",
      "published": 1756217108
    },
    {
      "id": "6ae3b4bb4183",
      "title": "中国国航伦敦飞北京航班迫降西伯利亚",
      "url": "https://www.dw.com/zh/中国国航伦敦飞北京航班迫降西伯利亚/a-73770080?maca=chi-rss-chi-news-3224-rdf",
      "source": "dw.com",
      "published": 1756210980
    },
    {
      "id": "0a4fb3cf383e",
      "title": "展示向日葵的土地：艾未未深入“战争腹地”拍摄关于乌克兰的电影",
      "url": "https://www.dw.com/zh/展示向日葵的土地：艾未未深入-战争腹地-拍摄关于乌克兰的电影/a-73758262?maca=chi-rss-chi-all-1127-rdf",
      "source": "dw.com",
      "published": 1756122900
    },
    {
      "id": "3970b41ddbef",
      "title": "纠结多年 柏林一种族主义地名终于改了！",
      "url": "https://www.dw.com/zh/纠结多年-柏林一种族主义地名终于改了！/a-73757955?maca=chi-rss-chi-all-1127-rdf",
      "source": "dw.com",
      "published": 1756119660
    },
    {
      "id": "3de3f9f8b6d2",
      "title": "德国小镇回收稀土 难敌中国竞争",
      "url": "https://www.dw.com/zh/德国小镇回收稀土-难敌中国竞争/a-73721609?maca=chi-rss-chi-all-1127-rdf",
      "source": "dw.com",
      "published": 1756019520
    },
    {
      "id": "6c937a324ca3",
      "title": "DW事实核查：如何识破AI生成的新闻播报视频",
      "url": "https://www.dw.com/zh/dw事实核查：如何识破ai生成的新闻播报视频/a-73715623?maca=chi-rss-chi-all-1127-rdf",
      "source": "dw.com",
      "published": 1756019460
    },
    {
      "id": "d0329fdb0b0c",
      "title": "德国仍拒绝向前殖民地支付赔偿金",
      "url": "https://www.dw.com/zh/德国仍拒绝向前殖民地支付赔偿金/a-73700522?maca=chi-rss-chi-all-1127-rdf",
      "source": "dw.com",
      "published": 1756019280
    },
    {
      "id": "b80c819f04df",
      "title": "台灣「大罷免」二輪投票與核三公投結果：專家點評",
      "url": "https://www.bbc.com/zhongwen/articles/cjeyppzewq8o/trad?at_medium=RSS&at_campaign=rss",
      "source": "bbc.com",
      "published": 1755962019
    },
    {
      "id": "be368b8a0d95",
      "title": "黄仁勋闪访台积电 称新款芯片出口中国将由华盛顿定夺",
      "url": "https://www.dw.com/zh/黄仁勋闪访台积电-称新款芯片出口中国将由华盛顿定夺/a-73735427?maca=chi-rss-chi-all-1127-rdf",
      "source": "dw.com",
      "published": 1755872880
    },
    {
      "id": "db135722fe06",
      "title": "Swatch廣告「瞇瞇眼」惹議下架 中網友怒轟",
      "url": "https://www.dw.com/zh/swatch廣告「瞇瞇眼」惹議下架-中網友怒轟/a-73698105?maca=chi-rss-chi-all-1127-rdf",
      "source": "dw.com",
      "published": 1755696060
    },
    {
      "id": "12445482b75f",
      "title": "特朗普为何对中国网开一面？",
      "url": "https://www.dw.com/zh/特朗普为何对中国网开一面？/a-73682188?maca=chi-rss-chi-all-1127-rdf",
      "source": "dw.com",
      "published": 1755595920
    },
    {
      "id": "87a6581371c7",
      "title": "德国数字主权路漫漫",
      "url": "https://www.dw.com/zh/德国数字主权路漫漫/a-73614719?maca=chi-rss-chi-all-1127-rdf",
      "source": "dw.com",
      "published": 1755416040
    },
    {
      "id": "650443392067",
      "title": "深圳“小孩哥姐”配送外卖“最后100米”引热议",
      "url": "https://www.dw.com/zh/深圳-小孩哥姐-配送外卖-最后100米-引热议/a-73644955?maca=chi-rss-chi-all-1127-rdf",
      "source": "dw.com",
      "published": 1755414060
    },
    {
      "id": "5d279b4541ac",
      "title": "中国“Z世代”女性热捧百年“女书”",
      "url": "https://www.dw.com/zh/中国-z世代-女性热捧百年-女书/a-73596329?maca=chi-rss-chi-all-1127-rdf",
      "source": "dw.com",
      "published": 1755414000
    },
    {
      "id": "0bdc3643609e",
      "title": "中国不再需要特供版高端芯片了？",
      "url": "https://www.dw.com/zh/中国不再需要特供版高端芯片了？/a-73621199?maca=chi-rss-chi-all-1127-rdf",
      "source": "dw.com",
      "published": 1755177000
    },
    {
      "id": "a229d8479ee9",
      "title": "黎智英「勾結外國勢力」案　一文看懂案情進展",
      "url": "https://www.bbc.com/zhongwen/articles/ce93rnlvng2o/trad?at_medium=RSS&at_campaign=rss",
      "source": "bbc.com",
      "published": 1755144870
    },
    {
      "id": "d087b6f864da",
      "title": "台灣工程師看台積電洩密：以前睜隻眼閉隻眼，現在一定要處理",
      "url": "https://www.bbc.com/zhongwen/articles/c39dr00mg2zo/trad?at_medium=RSS&at_campaign=rss",
      "source": "bbc.com",
      "published": 1755063097
    },
    {
      "id": "03b5a8089012",
      "title": "中国公民羁押期间死亡 律师吁华人移民小心行事",
      "url": "https://www.dw.com/zh/中国公民羁押期间死亡-律师吁华人移民小心行事/a-73613035?maca=chi-rss-chi-news-3224-rdf",
      "source": "dw.com",
      "published": 1754998800
    },
    {
      "id": "319f9bad6289",
      "title": "中國「外賣大戰」：誰在買單？ 迫於奔命的商家、騎手還是消費者？",
      "url": "https://www.bbc.com/zhongwen/articles/cn02wrk3w5ko/trad?at_medium=RSS&at_campaign=rss",
      "source": "bbc.com",
      "published": 1754986154
    },
    {
      "id": "44368f97d558",
      "title": "香港大學N號檔深偽圖片受害女生：「這是一個法律黑洞」",
      "url": "https://www.bbc.com/zhongwen/articles/cp94nmgde2xo/trad?at_medium=RSS&at_campaign=rss",
      "source": "bbc.com",
      "published": 1754903289
    },
    {
      "id": "b7f12daefbc7",
      "title": "中國人製造的「Made In Italy」如何改變普拉托？",
      "url": "https://www.dw.com/zh/中國人製造的「made-in-italy」如何改變普拉托？/a-73565674?maca=chi-rss-chi-all-1127-rdf",
      "source": "dw.com",
      "published": 1754627520
    },
    {
      "id": "37c8b1a798df",
      "title": "德国警方突查四州：打击涉嫌卖淫华人团伙",
      "url": "https://www.dw.com/zh/德国警方突查四州：打击涉嫌卖淫华人团伙/a-73556813?maca=chi-rss-chi-news-3224-rdf",
      "source": "dw.com",
      "published": 1754561280
    }
  ],
  "build_id": 1756924857
}